{"__type__":"sp.SkeletonData","_name":"skin4_fight2","_skeletonJson":{"skeleton":{"hash":"bNArP/lQ5Ek2ZZDYgqCFdxORQXk","spine":"3.6.53","width":231,"height":262,"images":"./images/"},"bones":[{"name":"root"},{"name":"5-shen","parent":"root","x":-15.76,"y":22.47},{"name":"5-shen3","parent":"5-shen","length":57.8,"rotation":86.34,"x":13.14,"y":-4.78},{"name":"5-tou","parent":"5-shen3","length":110.94,"rotation":-2.56,"x":60.32,"y":-2.16},{"name":"4-cao","parent":"5-tou","length":29.81,"rotation":124.66,"x":7.43,"y":45.16},{"name":"4-cao2","parent":"4-cao","length":40.89,"rotation":27.44,"x":29.81},{"name":"4-huangguang","parent":"5-tou","length":52.67,"rotation":-13.16,"x":105.56,"y":-6.08},{"name":"4-pifeng","parent":"5-shen3","length":26.97,"rotation":-107.71,"x":60.62,"y":-40.99},{"name":"4-weijin","parent":"5-tou","length":22.39,"rotation":-173.78,"x":-15.57,"y":21.92},{"name":"5-jiao1","parent":"5-shen","length":28.58,"rotation":-90,"x":-7.61,"y":3.95},{"name":"5-jiao2","parent":"5-shen","length":26.35,"rotation":-90,"x":35.52,"y":9.58,"scaleX":1.251},{"name":"5-lian","parent":"5-tou","length":40.4,"rotation":-83.78,"x":34.25,"y":28.45},{"name":"5-shou1","parent":"5-shen3","length":41.87,"rotation":147.5,"x":38.85,"y":34.22},{"name":"5-shou4","parent":"5-shen3","length":33.63,"rotation":-150.54,"x":40.38,"y":-41.19},{"name":"5-toufa","parent":"5-tou","length":44.79,"rotation":-85.18,"x":67.32,"y":12.27},{"name":"5-toufa2","parent":"5-toufa","length":42.83,"rotation":1.4,"x":82.69,"y":-8.91},{"name":"5-toufa3","parent":"5-toufa","length":28.96,"rotation":47.16,"x":6.83,"y":55.88},{"name":"5-toufa4","parent":"5-toufa","length":27.89,"rotation":-85.24,"x":-5.21,"y":-77.68},{"name":"5-weiba","parent":"5-shen3","length":20,"rotation":-50.12,"x":27.73,"y":-48.56},{"name":"5-weiba2","parent":"5-weiba","length":20.58,"rotation":6.21,"x":22.24,"y":0.69},{"name":"5-weiba3","parent":"5-weiba2","length":29.1,"rotation":-25.08,"x":20.58},{"name":"shadow","parent":"root","length":122.55,"rotation":0.42,"x":6.04,"y":16.23},{"name":"szh","parent":"root","x":312.59,"y":36.99}],"slots":[{"name":"shadow","bone":"shadow","attachment":"4"},{"name":"4-weiba2","bone":"5-weiba","attachment":"4"},{"name":"4-shou4","bone":"5-shou1","attachment":"4"},{"name":"4-jiao4","bone":"5-jiao1","attachment":"4"},{"name":"4-shen2","bone":"5-shen3","attachment":"4"},{"name":"4-jiao3","bone":"5-jiao2","attachment":"4"},{"name":"4-shou3","bone":"5-shou4","attachment":"4"},{"name":"4-weijin","bone":"4-weijin","attachment":"4"},{"name":"4-pifeng","bone":"4-pifeng","attachment":"4"},{"name":"4-toufa3","bone":"5-toufa","attachment":"4"},{"name":"4-toufa2","bone":"5-tou"},{"name":"5-tou","bone":"5-tou","attachment":"4"},{"name":"5-tou2","bone":"5-tou","attachment":"4"},{"name":"4-lian2","bone":"5-lian","attachment":"4"},{"name":"4-huangguang","bone":"4-huangguang","attachment":"4"},{"name":"4-cao","bone":"4-cao","attachment":"4"},{"name":"FX/szh","bone":"szh"}],"skins":{"default":{"4-lian2":{"4-lian1":{"x":2.14,"y":-8.89,"width":98,"height":77},"4-lian2":{"x":2.14,"y":-8.89,"width":97,"height":71}},"FX/szh":{"特效/szh":{"scaleX":2.024,"scaleY":2.024,"width":110,"height":110}}},"skin4":{"4-cao":{"4":{"name":"4-cao","type":"mesh","uvs":[1,0.23745,0.74452,0.38245,0.6624,0.45745,0.60926,0.58245,0.45469,1,0,1,0,0.44745,0.18418,0.20745,0.30977,0.11745,0.58511,0,1,0,0.52231,0.29745],"triangles":[2,11,1,9,10,0,11,8,9,1,11,9,0,1,9,3,11,2,7,8,11,5,6,4,11,6,7,3,6,11,3,4,6],"vertices":[1,4,1.71,11.79,1,2,5,-4.2,15.57,0.4,4,18.9,11.88,0.6,2,5,2.05,13.95,0.416,4,25.2,13.33,0.584,2,5,9.71,15.35,0.568,4,31.35,18.1,0.432,1,5,34.53,21.15,1,1,5,49.58,-1.06,1,1,5,23.5,-18.72,1,1,5,6.08,-17.4,1,2,5,-2.32,-14.14,0.4,4,34.26,-13.62,0.6,1,4,16.79,-11.77,1,1,4,-4.74,-0.11,1,2,5,-0.86,2,0.512,4,28.12,1.37,0.488],"hull":11,"edges":[0,20,8,10,10,12,18,20,18,22,22,4,6,22,22,16,22,14,22,2,2,0,2,4,4,6,6,8,12,14,14,16,16,18],"width":59,"height":57}},"4-huangguang":{"4":{"name":"4-huangguang","x":29.54,"y":-6.1,"rotation":-70.63,"width":67,"height":61}},"4-jiao3":{"4":{"name":"4-jiao2","x":12.01,"y":4.37,"rotation":90,"width":41,"height":38}},"4-jiao4":{"4":{"name":"4-jiao1","x":14.04,"y":2.28,"rotation":90,"width":44,"height":34}},"4-lian2":{"4":{"name":"4-lian","x":2.09,"y":-6.49,"width":97,"height":66}},"4-pifeng":{"4":{"name":"4-pifeng","x":11.16,"y":-1.74,"rotation":21.37,"width":54,"height":31}},"4-shen2":{"4":{"name":"4-shen","x":34.41,"y":-2.34,"rotation":-86.34,"width":98,"height":87}},"4-shou3":{"4":{"name":"4-shou2","x":22.29,"y":-0.95,"rotation":64.2,"width":50,"height":67}},"4-shou4":{"4":{"name":"4-shou1","x":17.43,"y":3.7,"rotation":126.16,"width":53,"height":72}},"4-toufa3":{"4":{"name":"4-toufa","type":"mesh","uvs":[0.94476,0.0541,0.91972,0.27182,1,0.42282,1,0.57733,0.92285,0.66512,0.94163,0.75291,0.81958,0.83368,0.75698,1,0.5799,0.96013,0.47532,1,0.21207,1,0.17601,0.95406,0.07503,0.95609,0,0.77804,0,0.35518,0.04258,0.28437,0.09487,0.08811,0.26256,0.05574,0.3473,0,0.84349,0],"triangles":[7,8,6,8,9,11,9,10,11,6,8,15,12,13,11,14,8,13,8,11,13,4,6,15,6,4,5,4,17,1,3,4,2,4,1,2,17,15,16,4,15,17,1,17,18,1,18,19,1,19,0,14,15,8],"vertices":[3,14,103.11,69.61,0.14722,16,75.54,-61.26,0.51282,15,22.33,78,0.33997,3,14,99.19,32.06,0.14483,16,45.34,-83.92,0.23577,15,17.5,40.55,0.6194,3,14,115.31,6.47,0.01168,16,37.54,-113.14,0.02257,15,32.99,14.58,0.96575,2,15,32.99,-12,0.9942,17,-47.33,125.53,0.0058,3,14,101.44,-35.55,0.01152,15,18.1,-27.1,0.92628,17,-33.13,109.78,0.06221,3,14,105.44,-50.56,0.02511,15,21.73,-42.2,0.86335,17,-17.84,112.51,0.11153,3,14,82.23,-65.02,0.10181,15,-1.83,-56.09,0.6342,17,-5.36,88.18,0.26399,3,14,70.85,-93.92,0.11075,15,-13.91,-84.7,0.44124,17,22.49,74.44,0.44801,3,14,36.51,-87.89,0.10975,15,-48.09,-77.84,0.22064,17,13.64,40.73,0.66961,3,14,16.5,-95.24,0.03207,15,-68.27,-84.7,0.06189,17,19.3,20.17,0.90604,3,14,-34.29,-96.48,0.0311,15,-119.08,-84.7,0.00004,17,16.32,-30.55,0.96886,3,14,-41.44,-88.75,0.07551,15,-126.04,-76.79,0.00002,17,8.02,-37.03,0.92447,3,14,-60.92,-89.57,0.13874,15,-145.53,-77.14,0.00001,17,7.22,-56.5,0.86126,4,14,-76.14,-59.31,0.29885,16,-140.88,-17.48,0.00606,15,-160.01,-46.52,0,17,-24.2,-69.16,0.69509,3,14,-77.91,13.4,0.60733,16,-88.77,33.26,0.24017,17,-96.8,-64.89,0.15251,3,14,-69.99,25.77,0.5663,16,-74.31,35.87,0.34125,17,-108.48,-55.97,0.09245,3,14,-60.73,59.77,0.38087,16,-43.08,52.18,0.60767,17,-141.58,-43.92,0.01147,3,14,-28.51,66.12,0.16943,16,-16.52,32.88,0.83041,17,-145.24,-11.28,0.00016,2,14,-12.39,76.11,0.02471,16,1.76,27.85,0.97529,3,14,83.34,78.44,0.14478,16,68.57,-40.76,0.58095,15,2.79,87.3,0.27428],"hull":20,"edges":[4,6,18,20,26,28,32,34,34,36,32,30,30,28,36,38,38,0,0,2,2,4,6,8,8,10,10,12,12,14,14,16,16,18,24,26,20,22,22,24],"width":193,"height":172}},"4-weiba2":{"4":{"name":"4-weiba","type":"mesh","uvs":[0,0.7875,0.18655,0.50937,0.40904,0.31071,0.49145,0.10594,0.66175,0,0.87875,0,1,0.31071,0.82107,0.46047,0.67549,0.54299,0.52716,0.50632,0.38157,0.69581,0.13161,1,0,1,0.49145,0.4024,0.2717,0.6194,0.60132,0.31377],"triangles":[15,3,4,2,3,15,5,15,4,6,15,5,6,7,15,8,9,15,7,8,15,13,2,15,9,13,15,13,1,2,14,13,9,13,14,1,10,14,9,0,1,14,11,12,0,14,11,0,11,14,10],"vertices":[1,18,-8.67,2.89,1,2,18,14.89,10.12,0.6532,19,-6.29,10.16,0.3468,2,19,16.2,8.71,0.83865,20,-7.66,6.03,0.16135,2,19,30.81,15.05,0.05558,20,2.89,17.97,0.94442,1,20,17.97,21.13,1,1,20,34.33,16.02,1,1,20,36.9,-7.89,1,2,19,33.05,-21.1,0.00804,20,20.23,-13.83,0.99196,2,19,20.6,-17.66,0.1788,20,7.51,-15.99,0.8212,3,18,36.73,-5.61,0.00038,19,13.71,-7.83,0.84187,20,-2.9,-10.01,0.15775,2,18,19.5,-9.67,0.81772,19,-3.85,-10,0.18228,1,18,-9.2,-15.42,1,1,18,-17.58,-9.28,1,1,19,16.61,-0.48,1,1,18,15.7,-0.16,1,1,20,6.77,1.29,1],"hull":13,"edges":[0,2,2,4,4,6,6,8,8,10,10,12,12,14,14,16,16,18,18,20,20,22,22,24,0,24],"width":79,"height":71}},"4-weijin":{"4":{"name":"4-weijin","x":7.26,"y":25.5,"rotation":90,"width":93,"height":40}},"5-tou":{"4":{"name":"4-toumao","x":17.28,"y":64.23,"rotation":-83.78,"width":29,"height":53}},"5-tou2":{"4":{"name":"4-tou","x":58.19,"y":11.85,"rotation":-83.78,"width":128,"height":137}},"shadow":{"4":{"name":"shadow","x":-0.65,"y":-2.84,"rotation":-0.42,"width":231,"height":74}}}},"events":{"skill":{}},"animations":{"fight2":{"slots":{"4-cao":{"color":[{"time":0,"color":"ffffff00","curve":"stepped"},{"time":0.0667,"color":"ffffff00"},{"time":0.3,"color":"ffffffff","curve":"stepped"},{"time":3.4,"color":"ffffffff"}]},"4-huangguang":{"color":[{"time":0,"color":"ffffff00","curve":"stepped"},{"time":0.0667,"color":"ffffff00"},{"time":0.3,"color":"ffffffff","curve":"stepped"},{"time":3.4,"color":"ffffffff"}]},"4-jiao3":{"color":[{"time":0,"color":"ffffff00","curve":"stepped"},{"time":0.0667,"color":"ffffff00"},{"time":0.3,"color":"ffffffff","curve":"stepped"},{"time":3.4,"color":"ffffffff"}]},"4-jiao4":{"color":[{"time":0,"color":"ffffff00","curve":"stepped"},{"time":0.0667,"color":"ffffff00"},{"time":0.3,"color":"ffffffff","curve":"stepped"},{"time":3.4,"color":"ffffffff"}]},"4-lian2":{"color":[{"time":0,"color":"ffffff00","curve":"stepped"},{"time":0.0667,"color":"ffffff00"},{"time":0.3,"color":"ffffffff","curve":"stepped"},{"time":3.4,"color":"ffffffff"}],"attachment":[{"time":0.6667,"name":"4-lian1"},{"time":1.4667,"name":"4"},{"time":1.9333,"name":"4-lian2"},{"time":2.8,"name":"4"}]},"4-pifeng":{"color":[{"time":0,"color":"ffffff00","curve":"stepped"},{"time":0.0667,"color":"ffffff00"},{"time":0.3,"color":"ffffffff","curve":"stepped"},{"time":3.4,"color":"ffffffff"}]},"4-shen2":{"color":[{"time":0,"color":"ffffff00","curve":"stepped"},{"time":0.0667,"color":"ffffff00"},{"time":0.3,"color":"ffffffff","curve":"stepped"},{"time":3.4,"color":"ffffffff"}]},"4-shou3":{"color":[{"time":0,"color":"ffffff00","curve":"stepped"},{"time":0.0667,"color":"ffffff00"},{"time":0.3,"color":"ffffffff","curve":"stepped"},{"time":3.4,"color":"ffffffff"}]},"4-shou4":{"color":[{"time":0,"color":"ffffff00","curve":"stepped"},{"time":0.0667,"color":"ffffff00"},{"time":0.3,"color":"ffffffff","curve":"stepped"},{"time":3.4,"color":"ffffffff"}]},"4-toufa2":{"color":[{"time":0,"color":"ffffff00","curve":"stepped"},{"time":0.0667,"color":"ffffff00"},{"time":0.3,"color":"ffffffff","curve":"stepped"},{"time":3.4,"color":"ffffffff"}]},"4-toufa3":{"color":[{"time":0,"color":"ffffff00","curve":"stepped"},{"time":0.0667,"color":"ffffff00"},{"time":0.3,"color":"ffffffff","curve":"stepped"},{"time":3.4,"color":"ffffffff"}]},"4-weiba2":{"color":[{"time":0,"color":"ffffff00","curve":"stepped"},{"time":0.0667,"color":"ffffff00"},{"time":0.3,"color":"ffffffff","curve":"stepped"},{"time":3.4,"color":"ffffffff"}]},"4-weijin":{"color":[{"time":0,"color":"ffffff00","curve":"stepped"},{"time":0.0667,"color":"ffffff00"},{"time":0.3,"color":"ffffffff","curve":"stepped"},{"time":3.4,"color":"ffffffff"}]},"5-tou":{"color":[{"time":0,"color":"ffffff00","curve":"stepped"},{"time":0.0667,"color":"ffffff00"},{"time":0.3,"color":"ffffffff","curve":"stepped"},{"time":3.4,"color":"ffffffff"}]},"5-tou2":{"color":[{"time":0,"color":"ffffff00","curve":"stepped"},{"time":0.0667,"color":"ffffff00"},{"time":0.3,"color":"ffffffff","curve":"stepped"},{"time":3.4,"color":"ffffffff"}]},"FX/szh":{"color":[{"time":0,"color":"ffffff00","curve":"stepped"},{"time":0.0667,"color":"ffffff00"},{"time":0.3,"color":"ffffff7f"},{"time":0.6667,"color":"ffffff00"},{"time":0.7667,"color":"ffffffff"},{"time":1,"color":"ffffff00"}],"attachment":[{"time":0.6667,"name":"特效/szh"},{"time":0.7667,"name":"特效/szh"}]},"shadow":{"color":[{"time":0,"color":"ffffff00","curve":"stepped"},{"time":0.0667,"color":"ffffff00"},{"time":0.3,"color":"ffffffff","curve":"stepped"},{"time":3.4,"color":"ffffffff"}]}},"bones":{"5-shen":{"rotate":[{"time":0,"angle":0,"curve":"stepped"},{"time":0.3,"angle":0,"curve":"stepped"},{"time":0.6333,"angle":0,"curve":"stepped"},{"time":0.7333,"angle":0,"curve":"stepped"},{"time":1.4,"angle":0,"curve":"stepped"},{"time":1.6333,"angle":0,"curve":"stepped"},{"time":1.9333,"angle":0,"curve":"stepped"},{"time":2.2,"angle":0,"curve":"stepped"},{"time":2.5333,"angle":0,"curve":"stepped"},{"time":2.8,"angle":0,"curve":"stepped"},{"time":3.4,"angle":0}],"translate":[{"time":0,"x":292.46,"y":-129.87,"curve":"stepped"},{"time":0.3,"x":292.46,"y":-129.87,"curve":"stepped"},{"time":0.6333,"x":292.46,"y":-129.87,"curve":"stepped"},{"time":0.7333,"x":295.74,"y":-124.95,"curve":"stepped"},{"time":0.8,"x":292.46,"y":-127.01,"curve":"stepped"},{"time":0.8667,"x":294.1,"y":-137.65,"curve":"stepped"},{"time":0.9333,"x":294.1,"y":-128.23,"curve":"stepped"},{"time":0.9667,"x":294.1,"y":-137.65,"curve":"stepped"},{"time":1,"x":289.18,"y":-126.59,"curve":"stepped"},{"time":1.0333,"x":292.46,"y":-129.87,"curve":"stepped"},{"time":1.0667,"x":289.18,"y":-126.59,"curve":"stepped"},{"time":1.1,"x":292.46,"y":-129.87,"curve":"stepped"},{"time":1.1333,"x":294.12,"y":-126.59,"curve":"stepped"},{"time":1.1667,"x":292.46,"y":-129.87,"curve":"stepped"},{"time":1.4,"x":292.46,"y":-129.87,"curve":"stepped"},{"time":1.6333,"x":292.46,"y":-129.87,"curve":"stepped"},{"time":1.9333,"x":292.46,"y":-129.87,"curve":"stepped"},{"time":2.2,"x":292.46,"y":-129.87,"curve":"stepped"},{"time":2.5333,"x":292.46,"y":-129.87,"curve":"stepped"},{"time":2.8,"x":292.46,"y":-129.87,"curve":"stepped"},{"time":3.4,"x":292.46,"y":-129.87}],"scale":[{"time":0,"x":1.3,"y":1.3,"curve":"stepped"},{"time":0.3,"x":1.3,"y":1.3,"curve":"stepped"},{"time":0.6333,"x":1.3,"y":1.3,"curve":"stepped"},{"time":0.7333,"x":1.3,"y":1.3,"curve":"stepped"},{"time":1.4,"x":1.3,"y":1.3,"curve":"stepped"},{"time":1.6333,"x":1.3,"y":1.3,"curve":"stepped"},{"time":1.9333,"x":1.3,"y":1.3,"curve":"stepped"},{"time":2.2,"x":1.3,"y":1.3,"curve":"stepped"},{"time":2.5333,"x":1.3,"y":1.3,"curve":"stepped"},{"time":2.8,"x":1.3,"y":1.3,"curve":"stepped"},{"time":3.4,"x":1.3,"y":1.3}],"shear":[{"time":0,"x":0,"y":0,"curve":"stepped"},{"time":0.3,"x":0,"y":0,"curve":"stepped"},{"time":0.6333,"x":0,"y":0,"curve":"stepped"},{"time":0.7333,"x":0,"y":0,"curve":"stepped"},{"time":1.4,"x":0,"y":0,"curve":"stepped"},{"time":1.6333,"x":0,"y":0,"curve":"stepped"},{"time":1.9333,"x":0,"y":0,"curve":"stepped"},{"time":2.2,"x":0,"y":0,"curve":"stepped"},{"time":2.5333,"x":0,"y":0,"curve":"stepped"},{"time":2.8,"x":0,"y":0,"curve":"stepped"},{"time":3.4,"x":0,"y":0}]},"5-jiao2":{"rotate":[{"time":0,"angle":0,"curve":"stepped"},{"time":0.3,"angle":0,"curve":"stepped"},{"time":0.6333,"angle":0,"curve":"stepped"},{"time":0.7333,"angle":0,"curve":"stepped"},{"time":1.4,"angle":0,"curve":"stepped"},{"time":1.6333,"angle":0,"curve":"stepped"},{"time":1.9333,"angle":0,"curve":"stepped"},{"time":2.2,"angle":0,"curve":"stepped"},{"time":2.5333,"angle":0,"curve":"stepped"},{"time":2.8,"angle":0,"curve":"stepped"},{"time":3.4,"angle":0}],"translate":[{"time":0,"x":0,"y":0,"curve":"stepped"},{"time":0.3,"x":0,"y":0,"curve":"stepped"},{"time":0.6333,"x":0,"y":0,"curve":"stepped"},{"time":0.7333,"x":0,"y":0,"curve":"stepped"},{"time":1.4,"x":0,"y":0,"curve":"stepped"},{"time":1.6333,"x":0,"y":0,"curve":"stepped"},{"time":1.9333,"x":0,"y":0,"curve":"stepped"},{"time":2.2,"x":0,"y":0,"curve":"stepped"},{"time":2.5333,"x":0,"y":0,"curve":"stepped"},{"time":2.8,"x":0,"y":0,"curve":"stepped"},{"time":3.4,"x":0,"y":0}],"scale":[{"time":0,"x":1,"y":1,"curve":"stepped"},{"time":0.3,"x":1,"y":1,"curve":"stepped"},{"time":0.6333,"x":1,"y":1,"curve":"stepped"},{"time":0.7333,"x":1,"y":1,"curve":"stepped"},{"time":1.4,"x":1,"y":1,"curve":"stepped"},{"time":1.6333,"x":1,"y":1,"curve":"stepped"},{"time":1.9333,"x":1,"y":1,"curve":"stepped"},{"time":2.2,"x":1,"y":1,"curve":"stepped"},{"time":2.5333,"x":1,"y":1,"curve":"stepped"},{"time":2.8,"x":1,"y":1,"curve":"stepped"},{"time":3.4,"x":1,"y":1}]},"5-jiao1":{"rotate":[{"time":0,"angle":0,"curve":"stepped"},{"time":0.3,"angle":0,"curve":"stepped"},{"time":0.6333,"angle":0},{"time":0.7333,"angle":3.84,"curve":"stepped"},{"time":1.4,"angle":3.84,"curve":"stepped"},{"time":1.6333,"angle":3.84,"curve":"stepped"},{"time":1.9333,"angle":3.84,"curve":"stepped"},{"time":2.2,"angle":3.84,"curve":"stepped"},{"time":2.5333,"angle":3.84,"curve":"stepped"},{"time":2.8,"angle":3.84},{"time":3.4,"angle":0}],"translate":[{"time":0,"x":0,"y":0,"curve":"stepped"},{"time":0.3,"x":0,"y":0,"curve":"stepped"},{"time":0.6333,"x":0,"y":0},{"time":0.7333,"x":0.63,"y":8.15,"curve":"stepped"},{"time":1.4,"x":0.63,"y":8.15,"curve":"stepped"},{"time":1.6333,"x":0.63,"y":8.15,"curve":"stepped"},{"time":1.9333,"x":0.63,"y":8.15,"curve":"stepped"},{"time":2.2,"x":0.63,"y":8.15,"curve":"stepped"},{"time":2.5333,"x":0.63,"y":8.15,"curve":"stepped"},{"time":2.8,"x":0.63,"y":8.15},{"time":3.4,"x":0,"y":0}],"scale":[{"time":0,"x":1,"y":1,"curve":"stepped"},{"time":0.3,"x":1,"y":1,"curve":"stepped"},{"time":0.6333,"x":1,"y":1},{"time":0.7333,"x":1.276,"y":1,"curve":"stepped"},{"time":1.4,"x":1.276,"y":1,"curve":"stepped"},{"time":1.6333,"x":1.276,"y":1,"curve":"stepped"},{"time":1.9333,"x":1.276,"y":1,"curve":"stepped"},{"time":2.2,"x":1.276,"y":1,"curve":"stepped"},{"time":2.5333,"x":1.276,"y":1,"curve":"stepped"},{"time":2.8,"x":1.276,"y":1},{"time":3.4,"x":1,"y":1}],"shear":[{"time":0.6333,"x":0,"y":0},{"time":0.7333,"x":-4.91,"y":0,"curve":"stepped"},{"time":1.4,"x":-4.91,"y":0},{"time":2.2,"x":-12.22,"y":0,"curve":"stepped"},{"time":2.5333,"x":-12.22,"y":0,"curve":"stepped"},{"time":2.8,"x":-12.22,"y":0,"curve":[0.393,0,0.511,1]},{"time":3.4,"x":1.39,"y":0}]},"5-shou1":{"rotate":[{"time":0,"angle":0,"curve":"stepped"},{"time":0.3,"angle":0,"curve":[0.035,0.73,0.511,1]},{"time":0.6333,"angle":27.15},{"time":0.7333,"angle":-0.56},{"time":1.4,"angle":1.62},{"time":1.6333,"angle":0},{"time":1.9333,"angle":18.46,"curve":"stepped"},{"time":2.2,"angle":18.46,"curve":"stepped"},{"time":2.5333,"angle":18.46,"curve":"stepped"},{"time":2.8,"angle":18.46,"curve":[0.393,0,0.511,1]},{"time":3.4,"angle":0}],"translate":[{"time":0,"x":0,"y":0,"curve":"stepped"},{"time":0.3,"x":0,"y":0,"curve":"stepped"},{"time":0.6333,"x":0,"y":0},{"time":0.7333,"x":12.34,"y":-1.29},{"time":1.4,"x":11.16,"y":-2.78},{"time":1.6333,"x":0,"y":0,"curve":"stepped"},{"time":1.9333,"x":0,"y":0,"curve":"stepped"},{"time":2.2,"x":0,"y":0,"curve":"stepped"},{"time":2.5333,"x":0,"y":0,"curve":"stepped"},{"time":2.8,"x":0,"y":0,"curve":"stepped"},{"time":3.4,"x":0,"y":0}],"scale":[{"time":0,"x":1,"y":1,"curve":"stepped"},{"time":0.3,"x":1,"y":1,"curve":"stepped"},{"time":0.6333,"x":1,"y":1,"curve":"stepped"},{"time":0.7333,"x":1,"y":1,"curve":"stepped"},{"time":1.4,"x":1,"y":1,"curve":"stepped"},{"time":1.6333,"x":1,"y":1,"curve":"stepped"},{"time":1.9333,"x":1,"y":1,"curve":"stepped"},{"time":2.2,"x":1,"y":1,"curve":"stepped"},{"time":2.5333,"x":1,"y":1,"curve":"stepped"},{"time":2.8,"x":1,"y":1,"curve":"stepped"},{"time":3.4,"x":1,"y":1}]},"5-lian":{"rotate":[{"time":0,"angle":0,"curve":"stepped"},{"time":0.3,"angle":0,"curve":"stepped"},{"time":0.6333,"angle":0,"curve":"stepped"},{"time":0.7333,"angle":0,"curve":"stepped"},{"time":1.4,"angle":0,"curve":"stepped"},{"time":1.6333,"angle":0,"curve":"stepped"},{"time":1.9333,"angle":0},{"time":2.2,"angle":1.05,"curve":[0.393,0,0.511,1]},{"time":2.5333,"angle":0,"curve":[0.019,0.74,0.524,1]},{"time":2.8,"angle":1.05,"curve":[0.393,0,0.511,1]},{"time":3.4,"angle":0}],"translate":[{"time":0,"x":0,"y":0,"curve":"stepped"},{"time":0.3,"x":0,"y":0,"curve":[0.035,0.73,0.511,1]},{"time":0.6333,"x":-7.32,"y":-1.9},{"time":0.7333,"x":3.94,"y":0.87,"curve":"stepped"},{"time":1.4,"x":3.94,"y":0.87},{"time":1.6333,"x":0,"y":0,"curve":"stepped"},{"time":1.9333,"x":0,"y":0},{"time":2.2,"x":2.47,"y":0.45,"curve":[0.393,0,0.511,1]},{"time":2.5333,"x":0,"y":0,"curve":[0.019,0.74,0.524,1]},{"time":2.8,"x":2.47,"y":0.45,"curve":[0.393,0,0.511,1]},{"time":3.1333,"x":0,"y":0,"curve":"stepped"},{"time":3.4,"x":0,"y":0}],"scale":[{"time":0,"x":1,"y":1,"curve":"stepped"},{"time":0.3,"x":1,"y":1,"curve":"stepped"},{"time":0.6333,"x":1,"y":1,"curve":"stepped"},{"time":0.7333,"x":1,"y":1,"curve":"stepped"},{"time":1.4,"x":1,"y":1,"curve":"stepped"},{"time":1.6333,"x":1,"y":1,"curve":"stepped"},{"time":1.9333,"x":1,"y":1,"curve":"stepped"},{"time":2.2,"x":1,"y":1,"curve":"stepped"},{"time":2.5333,"x":1,"y":1,"curve":"stepped"},{"time":2.8,"x":1,"y":1,"curve":"stepped"},{"time":3.4,"x":1,"y":1}]},"5-tou":{"rotate":[{"time":0,"angle":0,"curve":"stepped"},{"time":0.3,"angle":0,"curve":[0.035,0.73,0.511,1]},{"time":0.6333,"angle":15.76},{"time":0.7333,"angle":-17.37},{"time":1.4,"angle":-19.43},{"time":1.6333,"angle":0},{"time":1.9333,"angle":2.84,"curve":[0.035,0.73,0.511,1]},{"time":2.2,"angle":-11.21,"curve":[0.395,0,0.513,1]},{"time":2.5333,"angle":2.84,"curve":[0.019,0.74,0.524,1]},{"time":2.8,"angle":-11.21,"curve":[0.393,0,0.511,1]},{"time":3.4,"angle":0}],"translate":[{"time":0,"x":0,"y":0,"curve":"stepped"},{"time":0.3,"x":0,"y":0,"curve":[0.035,0.73,0.511,1]},{"time":0.6333,"x":-25.27,"y":14.27},{"time":0.7333,"x":11.02,"y":-2.52,"curve":"stepped"},{"time":1.4,"x":11.02,"y":-2.52},{"time":1.6333,"x":0,"y":0},{"time":1.9333,"x":-4.6,"y":2.02,"curve":[0.035,0.73,0.511,1]},{"time":2.2,"x":0,"y":0,"curve":[0.395,0,0.513,1]},{"time":2.5333,"x":-4.6,"y":2.02,"curve":[0.019,0.74,0.524,1]},{"time":2.8,"x":0,"y":0,"curve":"stepped"},{"time":3.4,"x":0,"y":0}],"scale":[{"time":0,"x":1,"y":1,"curve":"stepped"},{"time":0.3,"x":1,"y":1,"curve":"stepped"},{"time":0.6333,"x":1,"y":1,"curve":"stepped"},{"time":0.7333,"x":1,"y":1,"curve":"stepped"},{"time":1.4,"x":1,"y":1,"curve":"stepped"},{"time":1.6333,"x":1,"y":1,"curve":"stepped"},{"time":1.9333,"x":1,"y":1,"curve":"stepped"},{"time":2.2,"x":1,"y":1,"curve":"stepped"},{"time":2.5333,"x":1,"y":1,"curve":"stepped"},{"time":2.8,"x":1,"y":1,"curve":"stepped"},{"time":3.4,"x":1,"y":1}]},"5-shou4":{"rotate":[{"time":0,"angle":0,"curve":"stepped"},{"time":0.3,"angle":0,"curve":[0.035,0.73,0.511,1]},{"time":0.6333,"angle":16.14},{"time":0.7333,"angle":-12.45,"curve":"stepped"},{"time":1.4,"angle":-12.45},{"time":1.6333,"angle":0},{"time":1.9333,"angle":230.28,"curve":[0.035,0.73,0.511,1]},{"time":2.2,"angle":236.67,"curve":[0.393,0,0.511,1]},{"time":2.5333,"angle":230.28,"curve":[0.019,0.74,0.524,1]},{"time":2.8,"angle":236.67,"curve":[0.393,0,0.511,1]},{"time":3.4,"angle":0}],"translate":[{"time":0,"x":0,"y":0,"curve":"stepped"},{"time":0.3,"x":0,"y":0,"curve":"stepped"},{"time":0.6333,"x":0,"y":0,"curve":"stepped"},{"time":0.7333,"x":0,"y":0,"curve":"stepped"},{"time":1.4,"x":0,"y":0,"curve":"stepped"},{"time":1.6333,"x":0,"y":0},{"time":1.9333,"x":-5.1,"y":18.04,"curve":[0.035,0.73,0.511,1]},{"time":2.2,"x":-4.01,"y":15.24,"curve":[0.393,0,0.511,1]},{"time":2.5333,"x":-5.1,"y":18.04,"curve":[0.019,0.74,0.524,1]},{"time":2.8,"x":-4.01,"y":15.24,"curve":[0.393,0,0.511,1]},{"time":3.4,"x":0,"y":0}],"scale":[{"time":0,"x":1,"y":1,"curve":"stepped"},{"time":0.3,"x":1,"y":1,"curve":"stepped"},{"time":0.6333,"x":1,"y":1,"curve":"stepped"},{"time":0.7333,"x":1,"y":1,"curve":"stepped"},{"time":1.4,"x":1,"y":1,"curve":"stepped"},{"time":1.6333,"x":1,"y":1,"curve":"stepped"},{"time":1.9333,"x":1,"y":1,"curve":"stepped"},{"time":2.2,"x":1,"y":1,"curve":"stepped"},{"time":2.5333,"x":1,"y":1,"curve":"stepped"},{"time":2.8,"x":1,"y":1,"curve":"stepped"},{"time":3.4,"x":1,"y":1}]},"5-shen3":{"rotate":[{"time":0,"angle":0,"curve":"stepped"},{"time":0.3,"angle":0,"curve":[0.037,0.67,0.492,0.95]},{"time":0.6333,"angle":4.7},{"time":0.7333,"angle":-2.9,"curve":"stepped"},{"time":1.4,"angle":-2.9},{"time":1.6333,"angle":0},{"time":1.9333,"angle":8.91,"curve":"stepped"},{"time":2.2,"angle":8.91,"curve":"stepped"},{"time":2.5333,"angle":8.91,"curve":"stepped"},{"time":2.8,"angle":8.91,"curve":[0.393,0,0.511,1]},{"time":3.4,"angle":0}],"translate":[{"time":0,"x":0,"y":0,"curve":"stepped"},{"time":0.3,"x":0,"y":0,"curve":"stepped"},{"time":0.6333,"x":0,"y":0},{"time":0.7333,"x":0,"y":7.52,"curve":"stepped"},{"time":1.4,"x":0,"y":7.52},{"time":1.6333,"x":0,"y":0},{"time":1.9333,"x":0,"y":-2.38,"curve":"stepped"},{"time":2.2,"x":0,"y":-2.38,"curve":"stepped"},{"time":2.5333,"x":0,"y":-2.38,"curve":"stepped"},{"time":2.8,"x":0,"y":-2.38,"curve":[0.393,0,0.511,1]},{"time":3.4,"x":0,"y":0}],"scale":[{"time":0,"x":1,"y":1,"curve":"stepped"},{"time":0.3,"x":1,"y":1,"curve":"stepped"},{"time":0.6333,"x":1,"y":1,"curve":"stepped"},{"time":0.7333,"x":1,"y":1,"curve":"stepped"},{"time":1.4,"x":1,"y":1,"curve":"stepped"},{"time":1.6333,"x":1,"y":1,"curve":"stepped"},{"time":1.9333,"x":1,"y":1,"curve":"stepped"},{"time":2.2,"x":1,"y":1,"curve":"stepped"},{"time":2.5333,"x":1,"y":1,"curve":"stepped"},{"time":2.8,"x":1,"y":1,"curve":"stepped"},{"time":3.4,"x":1,"y":1}]},"5-weiba":{"rotate":[{"time":0,"angle":-3.57,"curve":[0.371,0.62,0.71,1]},{"time":0.0667,"angle":-4.47,"curve":[0.25,0,0.75,1]},{"time":0.5,"angle":4.82,"curve":[0.243,0,0.689,0.75]},{"time":0.8333,"angle":-3.57,"curve":[0.371,0.62,0.71,1]},{"time":0.9,"angle":-4.47,"curve":[0.25,0,0.75,1]},{"time":1.3333,"angle":4.82,"curve":[0.243,0,0.689,0.75]},{"time":1.6667,"angle":-3.57,"curve":[0.371,0.62,0.71,1]},{"time":1.7333,"angle":-4.47,"curve":[0.25,0,0.75,1]},{"time":2.1667,"angle":4.82,"curve":[0.243,0,0.689,0.75]},{"time":2.5,"angle":-3.57,"curve":[0.371,0.62,0.71,1]},{"time":2.5667,"angle":-4.47,"curve":[0.25,0,0.75,1]},{"time":3.0333,"angle":4.82,"curve":[0.243,0,0.689,0.75]},{"time":3.4,"angle":-3.57}],"translate":[{"time":0,"x":0,"y":0,"curve":"stepped"},{"time":0.3,"x":0,"y":0,"curve":"stepped"},{"time":0.6333,"x":0,"y":0,"curve":"stepped"},{"time":0.7333,"x":0,"y":0,"curve":"stepped"},{"time":1.4,"x":0,"y":0,"curve":"stepped"},{"time":1.6333,"x":0,"y":0,"curve":"stepped"},{"time":1.9333,"x":0,"y":0,"curve":"stepped"},{"time":2.2,"x":0,"y":0,"curve":"stepped"},{"time":2.5333,"x":0,"y":0,"curve":"stepped"},{"time":2.8,"x":0,"y":0,"curve":"stepped"},{"time":3.4,"x":0,"y":0}],"scale":[{"time":0,"x":1,"y":1,"curve":"stepped"},{"time":0.3,"x":1,"y":1,"curve":"stepped"},{"time":0.6333,"x":1,"y":1,"curve":"stepped"},{"time":0.7333,"x":1,"y":1,"curve":"stepped"},{"time":1.4,"x":1,"y":1,"curve":"stepped"},{"time":1.6333,"x":1,"y":1,"curve":"stepped"},{"time":1.9333,"x":1,"y":1,"curve":"stepped"},{"time":2.2,"x":1,"y":1,"curve":"stepped"},{"time":2.5333,"x":1,"y":1,"curve":"stepped"},{"time":2.8,"x":1,"y":1,"curve":"stepped"},{"time":3.4,"x":1,"y":1}]},"5-toufa3":{"rotate":[{"time":0,"angle":0,"curve":"stepped"},{"time":0.3,"angle":0,"curve":"stepped"},{"time":0.6333,"angle":0,"curve":"stepped"},{"time":0.7333,"angle":0},{"time":1.4,"angle":-4.06},{"time":1.6333,"angle":0,"curve":"stepped"},{"time":1.9333,"angle":0},{"time":2.2,"angle":3.8,"curve":[0.393,0,0.511,1]},{"time":2.5333,"angle":0,"curve":[0.019,0.74,0.524,1]},{"time":2.8,"angle":3.8,"curve":[0.393,0,0.511,1]},{"time":3.4,"angle":0}],"translate":[{"time":0,"x":0,"y":0,"curve":"stepped"},{"time":0.3,"x":0,"y":0,"curve":"stepped"},{"time":0.6333,"x":0,"y":0,"curve":"stepped"},{"time":0.7333,"x":0,"y":0},{"time":1.4,"x":4.86,"y":-1.51},{"time":1.6333,"x":0,"y":0,"curve":"stepped"},{"time":1.9333,"x":0,"y":0},{"time":2.2,"x":-7.03,"y":-2.04,"curve":[0.393,0,0.511,1]},{"time":2.5333,"x":0,"y":0,"curve":[0.019,0.74,0.524,1]},{"time":2.8,"x":-7.03,"y":-2.04,"curve":[0.393,0,0.511,1]},{"time":3.4,"x":0,"y":0}],"scale":[{"time":0,"x":1,"y":1,"curve":"stepped"},{"time":0.3,"x":1,"y":1,"curve":"stepped"},{"time":0.6333,"x":1,"y":1,"curve":"stepped"},{"time":0.7333,"x":1,"y":1,"curve":"stepped"},{"time":1.4,"x":1,"y":1,"curve":"stepped"},{"time":1.6333,"x":1,"y":1,"curve":"stepped"},{"time":1.9333,"x":1,"y":1,"curve":"stepped"},{"time":2.2,"x":1,"y":1,"curve":"stepped"},{"time":2.5333,"x":1,"y":1,"curve":"stepped"},{"time":2.8,"x":1,"y":1,"curve":"stepped"},{"time":3.4,"x":1,"y":1}]},"5-toufa":{"rotate":[{"time":0,"angle":0,"curve":"stepped"},{"time":0.3,"angle":0,"curve":"stepped"},{"time":0.6333,"angle":0,"curve":"stepped"},{"time":0.7333,"angle":0},{"time":1.4,"angle":2.3},{"time":1.6333,"angle":0,"curve":"stepped"},{"time":1.9333,"angle":0,"curve":"stepped"},{"time":2.2,"angle":0,"curve":"stepped"},{"time":2.5333,"angle":0,"curve":"stepped"},{"time":2.8,"angle":0,"curve":"stepped"},{"time":3.4,"angle":0}],"translate":[{"time":0,"x":0,"y":0,"curve":"stepped"},{"time":0.3,"x":0,"y":0,"curve":"stepped"},{"time":0.6333,"x":0,"y":0,"curve":"stepped"},{"time":0.7333,"x":0,"y":0,"curve":"stepped"},{"time":1.4,"x":0,"y":0,"curve":"stepped"},{"time":1.6333,"x":0,"y":0,"curve":"stepped"},{"time":1.9333,"x":0,"y":0,"curve":"stepped"},{"time":2.2,"x":0,"y":0,"curve":"stepped"},{"time":2.5333,"x":0,"y":0,"curve":"stepped"},{"time":2.8,"x":0,"y":0,"curve":"stepped"},{"time":3.4,"x":0,"y":0}],"scale":[{"time":0,"x":1,"y":1,"curve":"stepped"},{"time":0.3,"x":1,"y":1,"curve":"stepped"},{"time":0.6333,"x":1,"y":1,"curve":"stepped"},{"time":0.7333,"x":1,"y":1,"curve":"stepped"},{"time":1.4,"x":1,"y":1,"curve":"stepped"},{"time":1.6333,"x":1,"y":1,"curve":"stepped"},{"time":1.9333,"x":1,"y":1,"curve":"stepped"},{"time":2.2,"x":1,"y":1,"curve":"stepped"},{"time":2.5333,"x":1,"y":1,"curve":"stepped"},{"time":2.8,"x":1,"y":1,"curve":"stepped"},{"time":3.4,"x":1,"y":1}]},"5-toufa2":{"rotate":[{"time":0,"angle":0,"curve":"stepped"},{"time":0.3,"angle":0,"curve":"stepped"},{"time":0.6333,"angle":0,"curve":"stepped"},{"time":0.7333,"angle":0,"curve":"stepped"},{"time":1.4,"angle":0,"curve":"stepped"},{"time":1.6333,"angle":0,"curve":"stepped"},{"time":1.9333,"angle":0},{"time":2.2,"angle":2.38,"curve":[0.393,0,0.511,1]},{"time":2.5333,"angle":0,"curve":[0.019,0.74,0.524,1]},{"time":2.8,"angle":2.38,"curve":[0.393,0,0.511,1]},{"time":3.4,"angle":0}],"translate":[{"time":0,"x":0,"y":0,"curve":"stepped"},{"time":0.3,"x":0,"y":0,"curve":"stepped"},{"time":0.6333,"x":0,"y":0,"curve":"stepped"},{"time":0.7333,"x":0,"y":0},{"time":1.4,"x":0.61,"y":2.8},{"time":1.6333,"x":0,"y":0,"curve":"stepped"},{"time":1.9333,"x":0,"y":0},{"time":2.2,"x":-2.48,"y":1.43,"curve":[0.393,0,0.511,1]},{"time":2.5333,"x":0,"y":0,"curve":[0.019,0.74,0.524,1]},{"time":2.8,"x":-2.48,"y":1.43,"curve":[0.393,0,0.511,1]},{"time":3.4,"x":0,"y":0}],"scale":[{"time":0,"x":1,"y":1,"curve":"stepped"},{"time":0.3,"x":1,"y":1,"curve":"stepped"},{"time":0.6333,"x":1,"y":1,"curve":"stepped"},{"time":0.7333,"x":1,"y":1,"curve":"stepped"},{"time":1.4,"x":1,"y":1,"curve":"stepped"},{"time":1.6333,"x":1,"y":1,"curve":"stepped"},{"time":1.9333,"x":1,"y":1,"curve":"stepped"},{"time":2.2,"x":1,"y":1,"curve":"stepped"},{"time":2.5333,"x":1,"y":1,"curve":"stepped"},{"time":2.8,"x":1,"y":1,"curve":"stepped"},{"time":3.4,"x":1,"y":1}]},"5-toufa4":{"rotate":[{"time":0,"angle":0,"curve":"stepped"},{"time":0.3,"angle":0,"curve":"stepped"},{"time":0.6333,"angle":0,"curve":"stepped"},{"time":0.7333,"angle":0},{"time":1.4,"angle":2.92},{"time":1.6333,"angle":0,"curve":"stepped"},{"time":1.9333,"angle":0},{"time":2.2,"angle":2.33,"curve":[0.393,0,0.511,1]},{"time":2.5333,"angle":0,"curve":[0.019,0.74,0.524,1]},{"time":2.8,"angle":2.33,"curve":[0.393,0,0.511,1]},{"time":3.4,"angle":0}],"translate":[{"time":0,"x":0,"y":0,"curve":"stepped"},{"time":0.3,"x":0,"y":0,"curve":"stepped"},{"time":0.6333,"x":0,"y":0,"curve":"stepped"},{"time":0.7333,"x":0,"y":0},{"time":1.4,"x":3.7,"y":1.45},{"time":1.6333,"x":0,"y":0,"curve":"stepped"},{"time":1.9333,"x":0,"y":0},{"time":2.2,"x":2.33,"y":0.95,"curve":[0.393,0,0.511,1]},{"time":2.5333,"x":0,"y":0,"curve":[0.019,0.74,0.524,1]},{"time":2.8,"x":2.33,"y":0.95,"curve":[0.393,0,0.511,1]},{"time":3.4,"x":0,"y":0}],"scale":[{"time":0,"x":1,"y":1,"curve":"stepped"},{"time":0.3,"x":1,"y":1,"curve":"stepped"},{"time":0.6333,"x":1,"y":1,"curve":"stepped"},{"time":0.7333,"x":1,"y":1,"curve":"stepped"},{"time":1.4,"x":1,"y":1,"curve":"stepped"},{"time":1.6333,"x":1,"y":1,"curve":"stepped"},{"time":1.9333,"x":1,"y":1,"curve":"stepped"},{"time":2.2,"x":1,"y":1,"curve":"stepped"},{"time":2.5333,"x":1,"y":1,"curve":"stepped"},{"time":2.8,"x":1,"y":1,"curve":"stepped"},{"time":3.4,"x":1,"y":1}]},"shadow":{"rotate":[{"time":0,"angle":0,"curve":"stepped"},{"time":0.3,"angle":0,"curve":"stepped"},{"time":3.4,"angle":0}],"translate":[{"time":0,"x":278.78,"y":-142.03,"curve":"stepped"},{"time":0.3,"x":278.78,"y":-142.03},{"time":0.7333,"x":282.06,"y":-137.11,"curve":"stepped"},{"time":0.8,"x":278.78,"y":-139.17,"curve":"stepped"},{"time":0.8667,"x":280.42,"y":-149.81,"curve":"stepped"},{"time":0.9333,"x":280.42,"y":-140.39,"curve":"stepped"},{"time":0.9667,"x":280.42,"y":-149.81,"curve":"stepped"},{"time":1,"x":275.5,"y":-138.75,"curve":"stepped"},{"time":1.0333,"x":278.78,"y":-142.03,"curve":"stepped"},{"time":1.0667,"x":275.5,"y":-138.75,"curve":"stepped"},{"time":1.1,"x":278.78,"y":-142.03,"curve":"stepped"},{"time":1.1333,"x":280.44,"y":-138.75,"curve":"stepped"},{"time":1.1667,"x":278.78,"y":-142.03,"curve":"stepped"},{"time":3.4,"x":278.78,"y":-142.03}],"scale":[{"time":0,"x":1,"y":1,"curve":"stepped"},{"time":0.3,"x":1,"y":1,"curve":"stepped"},{"time":3.4,"x":1,"y":1}]},"szh":{"scale":[{"time":0.6667,"x":0.304,"y":0.304},{"time":0.7667,"x":1.772,"y":1.772},{"time":1,"x":3.813,"y":3.813}]},"4-cao":{"rotate":[{"time":0.3,"angle":0},{"time":0.6333,"angle":-9.09},{"time":0.7333,"angle":15.06},{"time":1.4,"angle":0},{"time":1.6333,"angle":-15.48},{"time":1.9333,"angle":0,"curve":[0.035,0.73,0.511,1]},{"time":2.2,"angle":7.28,"curve":[0.395,0,0.513,1]},{"time":2.5333,"angle":0,"curve":[0.019,0.74,0.524,1]},{"time":2.8,"angle":7.28},{"time":3.4,"angle":0}],"translate":[{"time":0.3,"x":0,"y":0},{"time":0.6333,"x":-6.99,"y":1.77},{"time":0.7333,"x":0,"y":0,"curve":"stepped"},{"time":1.4,"x":0,"y":0,"curve":"stepped"},{"time":1.6333,"x":0,"y":0,"curve":"stepped"},{"time":1.9333,"x":0,"y":0,"curve":"stepped"},{"time":2.2,"x":0,"y":0,"curve":"stepped"},{"time":2.5333,"x":0,"y":0,"curve":"stepped"},{"time":2.8,"x":0,"y":0,"curve":"stepped"},{"time":3.4,"x":0,"y":0}],"scale":[{"time":0.3,"x":1,"y":1,"curve":"stepped"},{"time":0.6333,"x":1,"y":1,"curve":"stepped"},{"time":0.7333,"x":1,"y":1,"curve":"stepped"},{"time":1.4,"x":1,"y":1,"curve":"stepped"},{"time":1.6333,"x":1,"y":1,"curve":"stepped"},{"time":1.9333,"x":1,"y":1,"curve":"stepped"},{"time":2.2,"x":1,"y":1,"curve":"stepped"},{"time":2.5333,"x":1,"y":1,"curve":"stepped"},{"time":2.8,"x":1,"y":1,"curve":"stepped"},{"time":3.4,"x":1,"y":1}]},"4-cao2":{"rotate":[{"time":0.3,"angle":0},{"time":0.6333,"angle":-9.09},{"time":0.7333,"angle":15.06},{"time":1.4,"angle":0},{"time":1.6333,"angle":-15.48},{"time":1.9333,"angle":0,"curve":[0.035,0.73,0.511,1]},{"time":2.2,"angle":7.28,"curve":[0.395,0,0.513,1]},{"time":2.5333,"angle":0,"curve":[0.019,0.74,0.524,1]},{"time":2.8,"angle":7.28},{"time":3.4,"angle":0}],"translate":[{"time":0.3,"x":0,"y":0,"curve":"stepped"},{"time":0.6333,"x":0,"y":0,"curve":"stepped"},{"time":0.7333,"x":0,"y":0,"curve":"stepped"},{"time":1.4,"x":0,"y":0,"curve":"stepped"},{"time":1.6333,"x":0,"y":0,"curve":"stepped"},{"time":1.9333,"x":0,"y":0,"curve":"stepped"},{"time":2.2,"x":0,"y":0,"curve":"stepped"},{"time":2.5333,"x":0,"y":0,"curve":"stepped"},{"time":2.8,"x":0,"y":0,"curve":"stepped"},{"time":3.4,"x":0,"y":0}],"scale":[{"time":0.3,"x":1,"y":1,"curve":"stepped"},{"time":0.6333,"x":1,"y":1,"curve":"stepped"},{"time":0.7333,"x":1,"y":1,"curve":"stepped"},{"time":1.4,"x":1,"y":1,"curve":"stepped"},{"time":1.6333,"x":1,"y":1,"curve":"stepped"},{"time":1.9333,"x":1,"y":1,"curve":"stepped"},{"time":2.2,"x":1,"y":1,"curve":"stepped"},{"time":2.5333,"x":1,"y":1,"curve":"stepped"},{"time":2.8,"x":1,"y":1,"curve":"stepped"},{"time":3.4,"x":1,"y":1}]},"5-weiba2":{"rotate":[{"time":0,"angle":-15.56,"curve":[0.381,0.54,0.744,1]},{"time":0.1667,"angle":-24.61,"curve":[0.25,0,0.75,1]},{"time":0.6,"angle":-1.39,"curve":[0.246,0,0.635,0.55]},{"time":0.8333,"angle":-15.56,"curve":[0.381,0.54,0.744,1]},{"time":1,"angle":-24.61,"curve":[0.25,0,0.75,1]},{"time":1.4333,"angle":-1.39,"curve":[0.246,0,0.635,0.55]},{"time":1.6667,"angle":-15.56,"curve":[0.381,0.54,0.744,1]},{"time":1.8333,"angle":-24.61,"curve":[0.25,0,0.75,1]},{"time":2.2667,"angle":-1.39,"curve":[0.246,0,0.635,0.55]},{"time":2.5,"angle":-15.56,"curve":[0.381,0.54,0.744,1]},{"time":2.6667,"angle":-24.61,"curve":[0.25,0,0.75,1]},{"time":3.1333,"angle":-1.39,"curve":[0.246,0,0.635,0.55]},{"time":3.4,"angle":-15.56}]},"5-weiba3":{"rotate":[{"time":0,"angle":14.29,"curve":[0.351,0.4,0.757,1]},{"time":0.2667,"angle":-13.86,"curve":[0.25,0,0.75,1]},{"time":0.7,"angle":25.44,"curve":[0.265,0,0.618,0.43]},{"time":0.8333,"angle":14.29,"curve":[0.351,0.4,0.757,1]},{"time":1.1,"angle":-13.86,"curve":[0.25,0,0.75,1]},{"time":1.5333,"angle":25.44,"curve":[0.265,0,0.618,0.43]},{"time":1.6667,"angle":14.29,"curve":[0.351,0.4,0.757,1]},{"time":1.9333,"angle":-13.86,"curve":[0.25,0,0.75,1]},{"time":2.3667,"angle":25.44,"curve":[0.265,0,0.618,0.43]},{"time":2.5,"angle":14.29,"curve":[0.351,0.4,0.757,1]},{"time":2.8,"angle":-13.86,"curve":[0.25,0,0.75,1]},{"time":3.2667,"angle":25.44,"curve":[0.265,0,0.618,0.43]},{"time":3.4,"angle":14.29}]}},"drawOrder":[{"time":0},{"time":0.3},{"time":1.8,"offsets":[{"slot":"4-shou3","offset":7}]},{"time":3.1},{"time":3.4}],"events":[{"time":0.8,"name":"skill"}]}}},"_atlasText":"\nskin4_fight2.png\nsize: 512,128\nformat: RGBA8888\nfilter: Linear,Linear\nrepeat: none\n4-cao\n  rotate: false\n  xy: 431, 97\n  size: 30, 29\n  orig: 30, 29\n  offset: 0, 0\n  index: -1\n4-huangguang\n  rotate: false\n  xy: 321, 95\n  size: 34, 31\n  orig: 34, 31\n  offset: 0, 0\n  index: -1\n4-jiao1\n  rotate: false\n  xy: 463, 109\n  size: 22, 17\n  orig: 22, 17\n  offset: 0, 0\n  index: -1\n4-jiao2\n  rotate: false\n  xy: 95, 2\n  size: 21, 19\n  orig: 21, 19\n  offset: 0, 0\n  index: -1\n4-lian\n  rotate: false\n  xy: 219, 93\n  size: 49, 33\n  orig: 49, 33\n  offset: 0, 0\n  index: -1\n4-lian1\n  rotate: true\n  xy: 229, 42\n  size: 49, 39\n  orig: 49, 39\n  offset: 0, 0\n  index: -1\n4-lian2\n  rotate: false\n  xy: 2, 2\n  size: 49, 36\n  orig: 49, 36\n  offset: 0, 0\n  index: -1\n4-pifeng\n  rotate: false\n  xy: 270, 42\n  size: 27, 16\n  orig: 27, 16\n  offset: 0, 0\n  index: -1\n4-shen\n  rotate: false\n  xy: 270, 82\n  size: 49, 44\n  orig: 49, 44\n  offset: 0, 0\n  index: -1\n4-shou1\n  rotate: true\n  xy: 357, 99\n  size: 27, 36\n  orig: 27, 36\n  offset: 0, 0\n  index: -1\n4-shou2\n  rotate: true\n  xy: 395, 101\n  size: 25, 34\n  orig: 25, 34\n  offset: 0, 0\n  index: -1\n4-tou\n  rotate: true\n  xy: 101, 23\n  size: 64, 69\n  orig: 64, 69\n  offset: 0, 0\n  index: -1\n4-toufa\n  rotate: false\n  xy: 2, 40\n  size: 97, 86\n  orig: 97, 86\n  offset: 0, 0\n  index: -1\n4-toumao\n  rotate: true\n  xy: 118, 6\n  size: 15, 27\n  orig: 15, 27\n  offset: 0, 0\n  index: -1\n4-weiba\n  rotate: false\n  xy: 53, 2\n  size: 40, 36\n  orig: 40, 36\n  offset: 0, 0\n  index: -1\n4-weijin\n  rotate: false\n  xy: 270, 60\n  size: 47, 20\n  orig: 47, 20\n  offset: 0, 0\n  index: -1\nshadow\n  rotate: false\n  xy: 101, 89\n  size: 116, 37\n  orig: 116, 37\n  offset: 0, 0\n  index: -1\n特效/szh\n  rotate: false\n  xy: 172, 32\n  size: 55, 55\n  orig: 55, 55\n  offset: 0, 0\n  index: -1\n","textures":[{"__uuid__":"6exteLuWFJl6jNSfGI2cIT"}],"textureNames":["skin4_fight2.png"]}