{"__type__":"sp.SkeletonData","_name":"effect","_skeletonJson":{"skeleton":{"hash":"TjK+cDwevYbIYgF0xNl84wit3QI","spine":"3.6.53","width":347.67,"height":123.79,"images":"./images/"},"bones":[{"name":"root"},{"name":"effect","parent":"root","color":"ffe900ff"},{"name":"5wuqi2","parent":"effect","length":83.91,"rotation":-180,"x":100.57,"y":21.96,"color":"e900ffff"},{"name":"skin5_fight1_a2","parent":"effect","scaleX":2.634,"scaleY":2.634,"color":"ffe900ff"},{"name":"骨骼","parent":"root"},{"name":"骨骼2","parent":"骨骼"},{"name":"骨骼3","parent":"骨骼"},{"name":"骨骼4","parent":"骨骼"},{"name":"骨骼5","parent":"骨骼"},{"name":"骨骼6","parent":"root"}],"slots":[{"name":"hit/qq_1","bone":"骨骼6","blend":"additive"},{"name":"5wuqi3","bone":"5wuqi2"},{"name":"hit/f_c2_1","bone":"skin5_fight1_a2","attachment":"hit/f_c1_2","blend":"additive"},{"name":"hit/s_f","bone":"骨骼5","color":"3b1f1f8e"},{"name":"hit/g_c1","bone":"骨骼3","blend":"additive"},{"name":"hit/b_b1","bone":"骨骼2","blend":"additive"},{"name":"hit/q_f","bone":"骨骼4","blend":"additive"}],"skins":{"default":{"5wuqi3":{"5wuqi":{"x":21.95,"y":27.14,"rotation":-176.1,"width":168,"height":86}},"hit/b_b1":{"hit/b_b1":{"scaleX":5.263,"scaleY":5.263,"width":64,"height":64}},"hit/f_c2_1":{"hit/f_c1_1":{"x":65,"width":132,"height":47},"hit/f_c1_2":{"x":65,"width":132,"height":47}},"hit/g_c1":{"hit/g_c1":{"scaleX":1.621,"scaleY":1.621,"width":128,"height":128}},"hit/q_f":{"hit/q_f":{"scaleX":1.485,"scaleY":1.485,"width":128,"height":128}},"hit/qq_1":{"hit/qq_1":{"width":128,"height":128}},"hit/s_f":{"hit/s_f":{"scaleX":0.945,"scaleY":0.945,"width":256,"height":256}}}},"animations":{"skin1_fight1_a":{"slots":{"hit/f_c2_1":{"attachment":[{"time":0,"name":"hit/f_c1_1"},{"time":0.0667,"name":"hit/f_c1_2"},{"time":0.1333,"name":"hit/f_c1_1"}]}},"bones":{"skin5_fight1_a2":{"scale":[{"time":0,"x":0.38,"y":0.38}]},"effect":{"scale":[{"time":0,"x":1,"y":1}]}}},"skin1_fight1_b":{"slots":{"hit/b_b1":{"color":[{"time":0,"color":"ffffff00"},{"time":0.0333,"color":"ffffffff","curve":"stepped"},{"time":0.1333,"color":"ffffffff"},{"time":0.2667,"color":"ffffff00"}],"attachment":[{"time":0,"name":"hit/b_b1"},{"time":0.1,"name":"hit/b_b1"},{"time":0.2667,"name":"hit/b_b1"}]},"hit/f_c2_1":{"attachment":[{"time":0,"name":null}]},"hit/g_c1":{"attachment":[{"time":0,"name":"hit/g_c1"},{"time":0.3,"name":null}]},"hit/q_f":{"color":[{"time":0,"color":"ffffffff","curve":"stepped"},{"time":0.0333,"color":"ffffffff"},{"time":0.1667,"color":"ffffff00"}],"attachment":[{"time":0,"name":"hit/q_f"}]},"hit/s_f":{"color":[{"time":0.1333,"color":"3b1f1f8e"},{"time":0.6333,"color":"3b1f1f00"}],"attachment":[{"time":0,"name":null},{"time":0.0333,"name":"hit/s_f"}]}},"bones":{"骨骼4":{"scale":[{"time":0,"x":0.201,"y":0.201},{"time":0.0667,"x":1,"y":1},{"time":0.1667,"x":1.32,"y":1.32}]},"骨骼5":{"scale":[{"time":0.0333,"x":0.201,"y":0.201},{"time":0.2333,"x":1,"y":1},{"time":0.6333,"x":1.32,"y":1.32}]},"骨骼2":{"scale":[{"time":0,"x":0.201,"y":0.201},{"time":0.1,"x":1,"y":1},{"time":0.2667,"x":1.32,"y":1.32}]},"骨骼3":{"scale":[{"time":0,"x":0.201,"y":0.201},{"time":0.1,"x":1,"y":1},{"time":0.2667,"x":1.32,"y":1.32}]}}},"skin2_fight1_a":{"slots":{"hit/f_c2_1":{"attachment":[{"time":0,"name":"hit/f_c1_1"},{"time":0.0667,"name":"hit/f_c1_2"},{"time":0.1333,"name":"hit/f_c1_1"}]}},"bones":{"skin5_fight1_a2":{"scale":[{"time":0,"x":0.38,"y":0.38}]}}},"skin2_fight1_b":{"slots":{"hit/b_b1":{"color":[{"time":0,"color":"ffffff00"},{"time":0.0333,"color":"ffffffff","curve":"stepped"},{"time":0.1333,"color":"ffffffff"},{"time":0.2667,"color":"ffffff00"}],"attachment":[{"time":0,"name":"hit/b_b1"},{"time":0.1,"name":"hit/b_b1"},{"time":0.2667,"name":"hit/b_b1"}]},"hit/f_c2_1":{"attachment":[{"time":0,"name":null}]},"hit/g_c1":{"attachment":[{"time":0,"name":"hit/g_c1"},{"time":0.3,"name":null}]},"hit/q_f":{"color":[{"time":0,"color":"ffffffff","curve":"stepped"},{"time":0.0333,"color":"ffffffff"},{"time":0.1667,"color":"ffffff00"}],"attachment":[{"time":0,"name":"hit/q_f"}]},"hit/s_f":{"color":[{"time":0.1333,"color":"3b1f1f8e"},{"time":0.6333,"color":"3b1f1f00"}],"attachment":[{"time":0,"name":null},{"time":0.0333,"name":"hit/s_f"}]}},"bones":{"骨骼5":{"scale":[{"time":0.0333,"x":0.201,"y":0.201},{"time":0.2333,"x":1,"y":1},{"time":0.6333,"x":1.32,"y":1.32}]},"骨骼2":{"scale":[{"time":0,"x":0.201,"y":0.201},{"time":0.1,"x":1,"y":1},{"time":0.2667,"x":1.32,"y":1.32}]},"骨骼4":{"scale":[{"time":0,"x":0.201,"y":0.201},{"time":0.0667,"x":1,"y":1},{"time":0.1667,"x":1.32,"y":1.32}]},"骨骼3":{"scale":[{"time":0,"x":0.201,"y":0.201},{"time":0.1,"x":1,"y":1},{"time":0.2667,"x":1.32,"y":1.32}]}}},"skin3_fight1_a":{"slots":{"hit/f_c2_1":{"attachment":[{"time":0,"name":"hit/f_c1_1"},{"time":0.0667,"name":"hit/f_c1_2"},{"time":0.1333,"name":"hit/f_c1_1"}]}},"bones":{"skin5_fight1_a2":{"scale":[{"time":0,"x":0.38,"y":0.38}]}}},"skin3_fight1_b":{"slots":{"hit/b_b1":{"color":[{"time":0,"color":"ffffff00"},{"time":0.0333,"color":"ffffffff","curve":"stepped"},{"time":0.1333,"color":"ffffffff"},{"time":0.2667,"color":"ffffff00"}],"attachment":[{"time":0,"name":"hit/b_b1"},{"time":0.1,"name":"hit/b_b1"},{"time":0.2667,"name":"hit/b_b1"}]},"hit/f_c2_1":{"attachment":[{"time":0,"name":null}]},"hit/g_c1":{"attachment":[{"time":0,"name":"hit/g_c1"},{"time":0.3,"name":null}]},"hit/q_f":{"color":[{"time":0,"color":"ffffffff","curve":"stepped"},{"time":0.0333,"color":"ffffffff"},{"time":0.1667,"color":"ffffff00"}],"attachment":[{"time":0,"name":"hit/q_f"}]},"hit/s_f":{"color":[{"time":0.1333,"color":"3b1f1f8e"},{"time":0.6333,"color":"3b1f1f00"}],"attachment":[{"time":0,"name":null},{"time":0.0333,"name":"hit/s_f"}]}},"bones":{"骨骼5":{"scale":[{"time":0.0333,"x":0.201,"y":0.201},{"time":0.2333,"x":1,"y":1},{"time":0.6333,"x":1.32,"y":1.32}]},"骨骼2":{"scale":[{"time":0,"x":0.201,"y":0.201},{"time":0.1,"x":1,"y":1},{"time":0.2667,"x":1.32,"y":1.32}]},"骨骼4":{"scale":[{"time":0,"x":0.201,"y":0.201},{"time":0.0667,"x":1,"y":1},{"time":0.1667,"x":1.32,"y":1.32}]},"骨骼3":{"scale":[{"time":0,"x":0.201,"y":0.201},{"time":0.1,"x":1,"y":1},{"time":0.2667,"x":1.32,"y":1.32}]}}},"skin4_fight1_a":{"slots":{"hit/f_c2_1":{"attachment":[{"time":0,"name":"hit/f_c1_1"},{"time":0.0667,"name":"hit/f_c1_2"},{"time":0.1333,"name":"hit/f_c1_1"}]}},"bones":{"skin5_fight1_a2":{"scale":[{"time":0,"x":0.38,"y":0.38}]}}},"skin4_fight1_b":{"slots":{"hit/b_b1":{"color":[{"time":0,"color":"ffffff00"},{"time":0.0333,"color":"ffffffff","curve":"stepped"},{"time":0.1333,"color":"ffffffff"},{"time":0.2667,"color":"ffffff00"}],"attachment":[{"time":0,"name":"hit/b_b1"},{"time":0.1,"name":"hit/b_b1"},{"time":0.2667,"name":"hit/b_b1"}]},"hit/f_c2_1":{"attachment":[{"time":0,"name":null}]},"hit/g_c1":{"attachment":[{"time":0,"name":"hit/g_c1"},{"time":0.3,"name":null}]},"hit/q_f":{"color":[{"time":0,"color":"ffffffff","curve":"stepped"},{"time":0.0333,"color":"ffffffff"},{"time":0.1667,"color":"ffffff00"}],"attachment":[{"time":0,"name":"hit/q_f"}]},"hit/s_f":{"color":[{"time":0.1333,"color":"3b1f1f8e"},{"time":0.6333,"color":"3b1f1f00"}],"attachment":[{"time":0,"name":null},{"time":0.0333,"name":"hit/s_f"}]}},"bones":{"骨骼5":{"scale":[{"time":0.0333,"x":0.201,"y":0.201},{"time":0.2333,"x":1,"y":1},{"time":0.6333,"x":1.32,"y":1.32}]},"骨骼2":{"scale":[{"time":0,"x":0.201,"y":0.201},{"time":0.1,"x":1,"y":1},{"time":0.2667,"x":1.32,"y":1.32}]},"骨骼4":{"scale":[{"time":0,"x":0.201,"y":0.201},{"time":0.0667,"x":1,"y":1},{"time":0.1667,"x":1.32,"y":1.32}]},"骨骼3":{"scale":[{"time":0,"x":0.201,"y":0.201},{"time":0.1,"x":1,"y":1},{"time":0.2667,"x":1.32,"y":1.32}]}}},"skin4_fight2_a":{"slots":{"5wuqi3":{"attachment":[{"time":0,"name":"5wuqi"},{"time":0.2667,"name":"5wuqi"}]},"hit/f_c2_1":{"attachment":[{"time":0,"name":null}]},"hit/qq_1":{"color":[{"time":0,"color":"f5a136ff"}],"attachment":[{"time":0,"name":"hit/qq_1"}]}},"bones":{"5wuqi2":{"rotate":[{"time":0,"angle":0},{"time":0.0667,"angle":90},{"time":0.1333,"angle":180},{"time":0.2,"angle":270},{"time":0.2667,"angle":0}],"translate":[{"time":0,"x":0,"y":-18.91,"curve":"stepped"},{"time":0.2667,"x":0,"y":-18.91}]},"骨骼6":{"rotate":[{"time":0,"angle":-90},{"time":0.0667,"angle":19.41},{"time":0.1333,"angle":90},{"time":0.2,"angle":-169.87},{"time":0.2667,"angle":-90}],"translate":[{"time":0,"x":99.45,"y":4.55,"curve":"stepped"},{"time":0.2667,"x":99.45,"y":4.55}],"scale":[{"time":0,"x":1.513,"y":1.513}]}}},"skin4_fight2_b":{"slots":{"hit/b_b1":{"color":[{"time":0,"color":"ffffff00"},{"time":0.0333,"color":"ffffffff","curve":"stepped"},{"time":0.1333,"color":"ffffffff"},{"time":0.2667,"color":"ffffff00"}],"attachment":[{"time":0,"name":"hit/b_b1"},{"time":0.1,"name":"hit/b_b1"},{"time":0.2667,"name":"hit/b_b1"}]},"hit/f_c2_1":{"attachment":[{"time":0,"name":null}]},"hit/g_c1":{"attachment":[{"time":0,"name":"hit/g_c1"},{"time":0.3,"name":null}]},"hit/q_f":{"color":[{"time":0,"color":"ffffffff","curve":"stepped"},{"time":0.0333,"color":"ffffffff"},{"time":0.1667,"color":"ffffff00"}],"attachment":[{"time":0,"name":"hit/q_f"}]},"hit/s_f":{"color":[{"time":0.1333,"color":"3b1f1f8e"},{"time":0.6333,"color":"3b1f1f00"}],"attachment":[{"time":0,"name":null},{"time":0.0333,"name":"hit/s_f"}]}},"bones":{"骨骼3":{"scale":[{"time":0,"x":0.201,"y":0.201},{"time":0.1,"x":1,"y":1},{"time":0.2667,"x":1.32,"y":1.32}]},"骨骼2":{"scale":[{"time":0,"x":0.201,"y":0.201},{"time":0.1,"x":1,"y":1},{"time":0.2667,"x":1.32,"y":1.32}]},"骨骼4":{"scale":[{"time":0,"x":0.201,"y":0.201},{"time":0.0667,"x":1,"y":1},{"time":0.1667,"x":1.32,"y":1.32}]},"骨骼5":{"scale":[{"time":0.0333,"x":0.201,"y":0.201},{"time":0.2333,"x":1,"y":1},{"time":0.6333,"x":1.32,"y":1.32}]}}},"skin5_fight1_a":{"slots":{"5wuqi3":{"attachment":[{"time":0,"name":"5wuqi"},{"time":0.2667,"name":"5wuqi"}]},"hit/f_c2_1":{"attachment":[{"time":0,"name":null}]},"hit/qq_1":{"color":[{"time":0,"color":"f5a136ff"}],"attachment":[{"time":0,"name":"hit/qq_1"}]}},"bones":{"5wuqi2":{"rotate":[{"time":0,"angle":0},{"time":0.0667,"angle":90},{"time":0.1333,"angle":180},{"time":0.2,"angle":270},{"time":0.2667,"angle":0}],"translate":[{"time":0,"x":0,"y":-18.91,"curve":"stepped"},{"time":0.2667,"x":0,"y":-18.91}]},"skin5_fight1_a2":{"scale":[{"time":0,"x":0.38,"y":0.38}]},"骨骼6":{"rotate":[{"time":0,"angle":-90},{"time":0.0667,"angle":19.41},{"time":0.1333,"angle":90},{"time":0.2,"angle":-169.87},{"time":0.2667,"angle":-90}],"translate":[{"time":0,"x":99.45,"y":4.55,"curve":"stepped"},{"time":0.2667,"x":99.45,"y":4.55}],"scale":[{"time":0,"x":1.513,"y":1.513}]}}},"skin5_fight1_b":{"slots":{"hit/b_b1":{"color":[{"time":0,"color":"ffffff00"},{"time":0.0333,"color":"ffffffff","curve":"stepped"},{"time":0.1333,"color":"ffffffff"},{"time":0.2667,"color":"ffffff00"}],"attachment":[{"time":0,"name":"hit/b_b1"},{"time":0.1,"name":"hit/b_b1"},{"time":0.2667,"name":"hit/b_b1"}]},"hit/f_c2_1":{"attachment":[{"time":0,"name":null}]},"hit/g_c1":{"attachment":[{"time":0,"name":"hit/g_c1"},{"time":0.3,"name":null}]},"hit/q_f":{"color":[{"time":0,"color":"ffffffff","curve":"stepped"},{"time":0.0333,"color":"ffffffff"},{"time":0.1667,"color":"ffffff00"}],"attachment":[{"time":0,"name":"hit/q_f"}]},"hit/s_f":{"color":[{"time":0.1333,"color":"3b1f1f8e"},{"time":0.6333,"color":"3b1f1f00"}],"attachment":[{"time":0,"name":null},{"time":0.0333,"name":"hit/s_f"}]}},"bones":{"骨骼5":{"scale":[{"time":0.0333,"x":0.201,"y":0.201},{"time":0.2333,"x":1,"y":1},{"time":0.6333,"x":1.32,"y":1.32}]},"骨骼2":{"scale":[{"time":0,"x":0.201,"y":0.201},{"time":0.1,"x":1,"y":1},{"time":0.2667,"x":1.32,"y":1.32}]},"骨骼4":{"scale":[{"time":0,"x":0.201,"y":0.201},{"time":0.0667,"x":1,"y":1},{"time":0.1667,"x":1.32,"y":1.32}]},"骨骼3":{"scale":[{"time":0,"x":0.201,"y":0.201},{"time":0.1,"x":1,"y":1},{"time":0.2667,"x":1.32,"y":1.32}]}}},"skin5_fight2_a":{"slots":{"5wuqi3":{"attachment":[{"time":0,"name":"5wuqi"},{"time":0.2667,"name":"5wuqi"}]},"hit/f_c2_1":{"attachment":[{"time":0,"name":null}]},"hit/qq_1":{"color":[{"time":0,"color":"f5a136ff"}],"attachment":[{"time":0,"name":"hit/qq_1"}]}},"bones":{"5wuqi2":{"rotate":[{"time":0,"angle":0},{"time":0.0667,"angle":90},{"time":0.1333,"angle":180},{"time":0.2,"angle":270},{"time":0.2667,"angle":0}],"translate":[{"time":0,"x":0,"y":-18.91,"curve":"stepped"},{"time":0.2667,"x":0,"y":-18.91}]},"骨骼6":{"rotate":[{"time":0,"angle":-90},{"time":0.0667,"angle":19.41},{"time":0.1333,"angle":90},{"time":0.2,"angle":-169.87},{"time":0.2667,"angle":-90}],"translate":[{"time":0,"x":99.45,"y":4.55,"curve":"stepped"},{"time":0.2667,"x":99.45,"y":4.55}],"scale":[{"time":0,"x":1.513,"y":1.513}]}}},"skin5_fight2_b":{"slots":{"hit/b_b1":{"color":[{"time":0,"color":"ffffff00"},{"time":0.0333,"color":"ffffffff","curve":"stepped"},{"time":0.1333,"color":"ffffffff"},{"time":0.2667,"color":"ffffff00"}],"attachment":[{"time":0,"name":"hit/b_b1"},{"time":0.1,"name":"hit/b_b1"},{"time":0.2667,"name":"hit/b_b1"}]},"hit/f_c2_1":{"attachment":[{"time":0,"name":null}]},"hit/g_c1":{"attachment":[{"time":0,"name":"hit/g_c1"},{"time":0.3,"name":null}]},"hit/q_f":{"color":[{"time":0,"color":"ffffffff","curve":"stepped"},{"time":0.0333,"color":"ffffffff"},{"time":0.1667,"color":"ffffff00"}],"attachment":[{"time":0,"name":"hit/q_f"}]},"hit/s_f":{"color":[{"time":0.1333,"color":"3b1f1f8e"},{"time":0.6333,"color":"3b1f1f00"}],"attachment":[{"time":0,"name":null},{"time":0.0333,"name":"hit/s_f"}]}},"bones":{"骨骼3":{"scale":[{"time":0,"x":0.201,"y":0.201},{"time":0.1,"x":1,"y":1},{"time":0.2667,"x":1.32,"y":1.32}]},"骨骼2":{"scale":[{"time":0,"x":0.201,"y":0.201},{"time":0.1,"x":1,"y":1},{"time":0.2667,"x":1.32,"y":1.32}]},"骨骼4":{"scale":[{"time":0,"x":0.201,"y":0.201},{"time":0.0667,"x":1,"y":1},{"time":0.1667,"x":1.32,"y":1.32}]},"骨骼5":{"scale":[{"time":0.0333,"x":0.201,"y":0.201},{"time":0.2333,"x":1,"y":1},{"time":0.6333,"x":1.32,"y":1.32}]}}}}},"_atlasText":"\neffect.png\nsize: 512,512\nformat: RGBA8888\nfilter: Linear,Linear\nrepeat: none\n5wuqi\n  rotate: false\n  xy: 2, 2\n  size: 168, 86\n  orig: 168, 86\n  offset: 0, 0\n  index: -1\nhit/b_b1\n  rotate: false\n  xy: 172, 24\n  size: 64, 64\n  orig: 64, 64\n  offset: 0, 0\n  index: -1\nhit/f_c1_1\n  rotate: true\n  xy: 390, 344\n  size: 132, 47\n  orig: 132, 47\n  offset: 0, 0\n  index: -1\nhit/f_c1_2\n  rotate: true\n  xy: 439, 344\n  size: 132, 47\n  orig: 132, 47\n  offset: 0, 0\n  index: -1\nhit/g_c1\n  rotate: false\n  xy: 260, 348\n  size: 128, 128\n  orig: 128, 128\n  offset: 0, 0\n  index: -1\nhit/q_f\n  rotate: false\n  xy: 132, 90\n  size: 128, 128\n  orig: 128, 128\n  offset: 0, 0\n  index: -1\nhit/qq_1\n  rotate: false\n  xy: 2, 90\n  size: 128, 128\n  orig: 128, 128\n  offset: 0, 0\n  index: -1\nhit/s_f\n  rotate: false\n  xy: 2, 220\n  size: 256, 256\n  orig: 256, 256\n  offset: 0, 0\n  index: -1\n","textures":[{"__uuid__":"7axpw0/U9J7oK4db9/Qi1x"}],"textureNames":["effect.png"]}