{"__type__":"cc.JsonAsset","_name":"SevenDayGoalConf","json":{"SevenDayGoalConf":{"1":{"conf":1,"day":1,"rank":1,"score":1,"task":1}},"day":{"1":[{"showItemId":20022,"task":1},{"showItemId":11101,"task":2},{"showItemId":11701,"task":3},{"showItemId":9,"task":4},{"showItemId":11401,"task":5},{"showItemId":11201,"task":6},{"showItemId":20022,"task":7}]},"rank":{"1":[{"max":1,"min":1,"rwId":55001},{"max":2,"min":2,"rwId":55002},{"max":3,"min":3,"rwId":55003},{"max":5,"min":4,"rwId":55004},{"max":10,"min":6,"rwId":55005},{"max":20,"min":11,"rwId":55006},{"max":50,"min":21,"rwId":55007},{"max":100,"min":51,"rwId":55008},{"max":1000,"min":101,"rwId":55009}]},"reward":{"1":[{"day":1,"param":[1],"point":100,"rwId":51001,"str":"游戏登录第{0}天"},{"day":2,"param":[2],"point":100,"rwId":51083,"str":"游戏登录{0}天"},{"day":3,"param":[3],"point":100,"rwId":51125,"str":"游戏登录{0}天"},{"day":4,"param":[4],"point":100,"rwId":51147,"str":"游戏登录第{0}天"},{"day":5,"param":[5],"point":100,"rwId":51169,"str":"游戏登录第{0}天"},{"day":6,"param":[6],"point":100,"rwId":51181,"str":"游戏登录第{0}天"},{"day":7,"param":[7],"point":100,"rwId":51193,"str":"游戏登录第{0}天"}],"2":[{"day":1,"param":[1],"point":100,"rwId":51002,"str":"通关副本第{0}章","windowId":1},{"day":1,"param":[2],"point":100,"rwId":51003,"str":"通关副本第{0}章","windowId":1},{"day":1,"param":[3],"point":100,"rwId":51004,"str":"通关副本第{0}章","windowId":1},{"day":1,"param":[4],"point":100,"rwId":51005,"str":"通关副本第{0}章","windowId":1},{"day":1,"param":[5],"point":100,"rwId":51006,"str":"通关副本第{0}章","windowId":1},{"day":1,"param":[6],"point":100,"rwId":51007,"str":"通关副本第{0}章","windowId":1},{"day":1,"param":[7],"point":100,"rwId":51008,"str":"通关副本第{0}章","windowId":1},{"day":1,"param":[8],"point":100,"rwId":51009,"str":"通关副本第{0}章","windowId":1},{"day":1,"param":[9],"point":100,"rwId":51010,"str":"通关副本第{0}章","windowId":1},{"day":1,"param":[10],"point":100,"rwId":51011,"str":"通关副本第{0}章","windowId":1},{"day":1,"param":[11],"point":100,"rwId":51012,"str":"通关副本第{0}章","windowId":1},{"day":1,"param":[12],"point":100,"rwId":51013,"str":"通关副本第{0}章","windowId":1},{"day":1,"param":[13],"point":100,"rwId":51014,"str":"通关副本第{0}章","windowId":1},{"day":1,"param":[14],"point":100,"rwId":51015,"str":"通关副本第{0}章","windowId":1},{"day":1,"param":[15],"point":100,"rwId":51016,"str":"通关副本第{0}章","windowId":1},{"day":1,"param":[16],"point":100,"rwId":51017,"str":"通关副本第{0}章","windowId":1},{"day":1,"param":[17],"point":100,"rwId":51018,"str":"通关副本第{0}章","windowId":1},{"day":1,"param":[18],"point":100,"rwId":51019,"str":"通关副本第{0}章","windowId":1},{"day":1,"param":[19],"point":100,"rwId":51020,"str":"通关副本第{0}章","windowId":1},{"day":1,"param":[20],"point":100,"rwId":51021,"str":"通关副本第{0}章","windowId":1},{"day":1,"param":[21],"point":100,"rwId":51022,"str":"通关副本第{0}章","windowId":1},{"day":1,"param":[22],"point":100,"rwId":51023,"str":"通关副本第{0}章","windowId":1},{"day":1,"param":[23],"point":100,"rwId":51024,"str":"通关副本第{0}章","windowId":1},{"day":1,"param":[24],"point":100,"rwId":51025,"str":"通关副本第{0}章","windowId":1},{"day":1,"param":[25],"point":100,"rwId":51026,"str":"通关副本第{0}章","windowId":1},{"day":1,"param":[26],"point":100,"rwId":51027,"str":"通关副本第{0}章","windowId":1},{"day":1,"param":[27],"point":100,"rwId":51028,"str":"通关副本第{0}章","windowId":1},{"day":1,"param":[28],"point":100,"rwId":51029,"str":"通关副本第{0}章","windowId":1},{"day":1,"param":[29],"point":100,"rwId":51030,"str":"通关副本第{0}章","windowId":1},{"day":1,"param":[30],"point":100,"rwId":51031,"str":"通关副本第{0}章","windowId":1}],"3":[{"day":1,"param":[2,2],"point":100,"rwId":51032,"str":"收集B级以上卡牌{0}张","subType":1,"windowId":20900},{"day":1,"param":[4,2],"point":100,"rwId":51033,"str":"收集B级以上卡牌{0}张","subType":1,"windowId":20900},{"day":1,"param":[6,2],"point":100,"rwId":51034,"str":"收集B级以上卡牌{0}张","subType":1,"windowId":20900},{"day":1,"param":[8,2],"point":100,"rwId":51035,"str":"收集B级以上卡牌{0}张","subType":1,"windowId":20900},{"day":1,"param":[10,2],"point":100,"rwId":51036,"str":"收集B级以上卡牌{0}张","subType":1,"windowId":20900},{"day":1,"param":[12,2],"point":100,"rwId":51037,"str":"收集B级以上卡牌{0}张","subType":1,"windowId":20900},{"day":1,"param":[14,2],"point":100,"rwId":51038,"str":"收集B级以上卡牌{0}张","subType":1,"windowId":20900},{"day":1,"param":[16,2],"point":100,"rwId":51039,"str":"收集B级以上卡牌{0}张","subType":1,"windowId":20900},{"day":1,"param":[18,2],"point":100,"rwId":51040,"str":"收集B级以上卡牌{0}张","subType":1,"windowId":20900},{"day":1,"param":[20,2],"point":100,"rwId":51041,"str":"收集B级以上卡牌{0}张","subType":1,"windowId":20900}],"4":[{"day":1,"param":[2],"point":100,"rwId":51042,"str":"卡牌等级达到{0}级","subType":2,"windowId":10308},{"day":1,"param":[4],"point":100,"rwId":51043,"str":"卡牌等级达到{0}级","subType":2,"windowId":10308},{"day":1,"param":[6],"point":100,"rwId":51044,"str":"卡牌等级达到{0}级","subType":2,"windowId":10308},{"day":1,"param":[8],"point":100,"rwId":51045,"str":"卡牌等级达到{0}级","subType":2,"windowId":10308},{"day":1,"param":[10],"point":100,"rwId":51046,"str":"卡牌等级达到{0}级","subType":2,"windowId":10308},{"day":1,"param":[12],"point":100,"rwId":51047,"str":"卡牌等级达到{0}级","subType":2,"windowId":10308},{"day":1,"param":[14],"point":100,"rwId":51048,"str":"卡牌等级达到{0}级","subType":2,"windowId":10308},{"day":1,"param":[16],"point":100,"rwId":51049,"str":"卡牌等级达到{0}级","subType":2,"windowId":10308},{"day":1,"param":[18],"point":100,"rwId":51050,"str":"卡牌等级达到{0}级","subType":2,"windowId":10308},{"day":1,"param":[20],"point":100,"rwId":51051,"str":"卡牌等级达到{0}级","subType":2,"windowId":10308}],"5":[{"day":1,"param":[2],"point":100,"rwId":51052,"str":"卡牌技能等级达到{0}级","subType":3,"windowId":10410},{"day":1,"param":[4],"point":100,"rwId":51053,"str":"卡牌技能等级达到{0}级","subType":3,"windowId":10410},{"day":1,"param":[6],"point":100,"rwId":51054,"str":"卡牌技能等级达到{0}级","subType":3,"windowId":10410},{"day":1,"param":[8],"point":100,"rwId":51055,"str":"卡牌技能等级达到{0}级","subType":3,"windowId":10410},{"day":1,"param":[10],"point":100,"rwId":51056,"str":"卡牌技能等级达到{0}级","subType":3,"windowId":10410},{"day":1,"param":[12],"point":100,"rwId":51057,"str":"卡牌技能等级达到{0}级","subType":3,"windowId":10410},{"day":1,"param":[14],"point":100,"rwId":51058,"str":"卡牌技能等级达到{0}级","subType":3,"windowId":10410},{"day":1,"param":[16],"point":100,"rwId":51059,"str":"卡牌技能等级达到{0}级","subType":3,"windowId":10410},{"day":1,"param":[18],"point":100,"rwId":51060,"str":"卡牌技能等级达到{0}级","subType":3,"windowId":10410},{"day":1,"param":[20],"point":100,"rwId":51061,"str":"卡牌技能等级达到{0}级","subType":3,"windowId":10410}],"6":[{"day":1,"param":[1],"point":100,"rwId":51062,"str":"祭坛抽奖{0}次","subType":13,"windowId":20900},{"day":1,"param":[5],"point":100,"rwId":51063,"str":"祭坛抽奖{0}次","subType":13,"windowId":20900},{"day":1,"param":[10],"point":100,"rwId":51064,"str":"祭坛抽奖{0}次","subType":13,"windowId":20900},{"day":1,"param":[15],"point":100,"rwId":51065,"str":"祭坛抽奖{0}次","subType":13,"windowId":20900},{"day":1,"param":[20],"point":100,"rwId":51066,"str":"祭坛抽奖{0}次","subType":13,"windowId":20900},{"day":1,"param":[25],"point":100,"rwId":51067,"str":"祭坛抽奖{0}次","subType":13,"windowId":20900},{"day":1,"param":[30],"point":100,"rwId":51068,"str":"祭坛抽奖{0}次","subType":13,"windowId":20900},{"day":1,"param":[35],"point":100,"rwId":51069,"str":"祭坛抽奖{0}次","subType":13,"windowId":20900},{"day":1,"param":[40],"point":100,"rwId":51070,"str":"祭坛抽奖{0}次","subType":13,"windowId":20900},{"day":1,"param":[45],"point":100,"rwId":51071,"str":"祭坛抽奖{0}次","subType":13,"windowId":20900},{"day":1,"param":[50],"point":100,"rwId":51072,"str":"祭坛抽奖{0}次","subType":13,"windowId":20900},{"day":1,"param":[55],"point":100,"rwId":51073,"str":"祭坛抽奖{0}次","subType":13,"windowId":20900},{"day":1,"param":[60],"point":100,"rwId":51074,"str":"祭坛抽奖{0}次","subType":13,"windowId":20900},{"day":1,"param":[65],"point":100,"rwId":51075,"str":"祭坛抽奖{0}次","subType":13,"windowId":20900},{"day":1,"param":[70],"point":100,"rwId":51076,"str":"祭坛抽奖{0}次","subType":13,"windowId":20900},{"day":1,"param":[75],"point":100,"rwId":51077,"str":"祭坛抽奖{0}次","subType":13,"windowId":20900},{"day":1,"param":[80],"point":100,"rwId":51078,"str":"祭坛抽奖{0}次","subType":13,"windowId":20900},{"day":1,"param":[85],"point":100,"rwId":51079,"str":"祭坛抽奖{0}次","subType":13,"windowId":20900},{"day":1,"param":[90],"point":100,"rwId":51080,"str":"祭坛抽奖{0}次","subType":13,"windowId":20900},{"day":1,"param":[100],"point":100,"rwId":51081,"str":"祭坛抽奖{0}次","subType":13,"windowId":20900}],"7":[{"day":1,"param":[6],"point":100,"rwId":51082,"str":"累计充值达到{0}元","windowId":20100},{"day":2,"param":[15],"point":100,"rwId":51124,"str":"累计充值达到{0}元","windowId":20100},{"day":3,"param":[30],"point":100,"rwId":51146,"str":"累计充值达到{0}元","windowId":20100},{"day":4,"param":[50],"point":100,"rwId":51168,"str":"累计充值达到{0}元","windowId":20100},{"day":5,"param":[80],"point":100,"rwId":51180,"str":"累计充值达到{0}元","windowId":20100},{"day":6,"param":[100],"point":100,"rwId":51192,"str":"累计充值达到{0}元","windowId":20100},{"day":7,"param":[200],"point":100,"rwId":51210,"str":"累计充值达到{0}元","windowId":20100}],"9":[{"day":2,"param":[20],"point":100,"rwId":51084,"str":"装备强化达到{0}次","subType":4,"windowId":60110},{"day":2,"param":[40],"point":100,"rwId":51085,"str":"装备强化达到{0}次","subType":4,"windowId":60110},{"day":2,"param":[60],"point":100,"rwId":51086,"str":"装备强化达到{0}次","subType":4,"windowId":60110},{"day":2,"param":[80],"point":100,"rwId":51087,"str":"装备强化达到{0}次","subType":4,"windowId":60110},{"day":2,"param":[100],"point":100,"rwId":51088,"str":"装备强化达到{0}次","subType":4,"windowId":60110},{"day":2,"param":[120],"point":100,"rwId":51089,"str":"装备强化达到{0}次","subType":4,"windowId":60110},{"day":2,"param":[140],"point":100,"rwId":51090,"str":"装备强化达到{0}次","subType":4,"windowId":60110},{"day":2,"param":[160],"point":100,"rwId":51091,"str":"装备强化达到{0}次","subType":4,"windowId":60110},{"day":2,"param":[180],"point":100,"rwId":51092,"str":"装备强化达到{0}次","subType":4,"windowId":60110},{"day":2,"param":[200],"point":100,"rwId":51093,"str":"装备强化达到{0}次","subType":4,"windowId":60110},{"day":2,"param":[220],"point":100,"rwId":51094,"str":"装备强化达到{0}次","subType":4,"windowId":60110},{"day":2,"param":[240],"point":100,"rwId":51095,"str":"装备强化达到{0}次","subType":4,"windowId":60110},{"day":2,"param":[260],"point":100,"rwId":51096,"str":"装备强化达到{0}次","subType":4,"windowId":60110},{"day":2,"param":[280],"point":100,"rwId":51097,"str":"装备强化达到{0}次","subType":4,"windowId":60110},{"day":2,"param":[300],"point":100,"rwId":51098,"str":"装备强化达到{0}次","subType":4,"windowId":60110},{"day":2,"param":[320],"point":100,"rwId":51099,"str":"装备强化达到{0}次","subType":4,"windowId":60110},{"day":2,"param":[340],"point":100,"rwId":51100,"str":"装备强化达到{0}次","subType":4,"windowId":60110},{"day":2,"param":[360],"point":100,"rwId":51101,"str":"装备强化达到{0}次","subType":4,"windowId":60110},{"day":2,"param":[380],"point":100,"rwId":51102,"str":"装备强化达到{0}次","subType":4,"windowId":60110},{"day":2,"param":[400],"point":100,"rwId":51103,"str":"装备强化达到{0}次","subType":4,"windowId":60110}],"10":[{"day":2,"param":[2],"point":100,"rwId":51104,"str":"装备升阶达到{0}次","subType":5,"windowId":60120},{"day":2,"param":[4],"point":100,"rwId":51105,"str":"装备升阶达到{0}次","subType":5,"windowId":60120},{"day":2,"param":[6],"point":100,"rwId":51106,"str":"装备升阶达到{0}次","subType":5,"windowId":60120},{"day":2,"param":[8],"point":100,"rwId":51107,"str":"装备升阶达到{0}次","subType":5,"windowId":60120},{"day":2,"param":[10],"point":100,"rwId":51108,"str":"装备升阶达到{0}次","subType":5,"windowId":60120},{"day":2,"param":[12],"point":100,"rwId":51109,"str":"装备升阶达到{0}次","subType":5,"windowId":60120},{"day":2,"param":[14],"point":100,"rwId":51110,"str":"装备升阶达到{0}次","subType":5,"windowId":60120},{"day":2,"param":[16],"point":100,"rwId":51111,"str":"装备升阶达到{0}次","subType":5,"windowId":60120},{"day":2,"param":[18],"point":100,"rwId":51112,"str":"装备升阶达到{0}次","subType":5,"windowId":60120},{"day":2,"param":[20],"point":100,"rwId":51113,"str":"装备升阶达到{0}次","subType":5,"windowId":60120}],"11":[{"day":2,"param":[1],"point":100,"rwId":51114,"str":"远征到达{0}层","windowId":30100},{"day":2,"param":[3],"point":100,"rwId":51115,"str":"远征到达{0}层","windowId":30100},{"day":2,"param":[5],"point":100,"rwId":51116,"str":"远征到达{0}层","windowId":30100},{"day":2,"param":[10],"point":100,"rwId":51117,"str":"远征到达{0}层","windowId":30100},{"day":2,"param":[15],"point":100,"rwId":51118,"str":"远征到达{0}层","windowId":30100},{"day":2,"param":[20],"point":100,"rwId":51119,"str":"远征到达{0}层","windowId":30100},{"day":2,"param":[25],"point":100,"rwId":51120,"str":"远征到达{0}层","windowId":30100},{"day":2,"param":[30],"point":100,"rwId":51121,"str":"远征到达{0}层","windowId":30100},{"day":2,"param":[35],"point":100,"rwId":51122,"str":"远征到达{0}层","windowId":30100},{"day":2,"param":[40],"point":100,"rwId":51123,"str":"远征到达{0}层","windowId":30100}],"14":[{"day":3,"param":[3],"point":100,"rwId":51126,"str":"神器注灵{0}次","subType":6,"windowId":56000},{"day":3,"param":[5],"point":100,"rwId":51127,"str":"神器注灵{0}次","subType":6,"windowId":56000},{"day":3,"param":[10],"point":100,"rwId":51128,"str":"神器注灵{0}次","subType":6,"windowId":56000},{"day":3,"param":[20],"point":100,"rwId":51129,"str":"神器注灵{0}次","subType":6,"windowId":56000},{"day":3,"param":[30],"point":100,"rwId":51130,"str":"神器注灵{0}次","subType":6,"windowId":56000},{"day":3,"param":[40],"point":100,"rwId":51131,"str":"神器注灵{0}次","subType":6,"windowId":56000},{"day":3,"param":[50],"point":100,"rwId":51132,"str":"神器注灵{0}次","subType":6,"windowId":56000},{"day":3,"param":[60],"point":100,"rwId":51133,"str":"神器注灵{0}次","subType":6,"windowId":56000},{"day":3,"param":[80],"point":100,"rwId":51134,"str":"神器注灵{0}次","subType":6,"windowId":56000},{"day":3,"param":[100],"point":100,"rwId":51135,"str":"神器注灵{0}次","subType":6,"windowId":56000}],"15":[{"day":3,"param":[5],"point":100,"rwId":51136,"str":"每日副本通关{0}次","windowId":57002},{"day":3,"param":[10],"point":100,"rwId":51137,"str":"每日副本通关{0}次","windowId":57002},{"day":3,"param":[15],"point":100,"rwId":51138,"str":"每日副本通关{0}次","windowId":57002},{"day":3,"param":[20],"point":100,"rwId":51139,"str":"每日副本通关{0}次","windowId":57002},{"day":3,"param":[25],"point":100,"rwId":51140,"str":"每日副本通关{0}次","windowId":57002},{"day":3,"param":[30],"point":100,"rwId":51141,"str":"每日副本通关{0}次","windowId":57002},{"day":3,"param":[35],"point":100,"rwId":51142,"str":"每日副本通关{0}次","windowId":57002},{"day":3,"param":[40],"point":100,"rwId":51143,"str":"每日副本通关{0}次","windowId":57002},{"day":3,"param":[45],"point":100,"rwId":51144,"str":"每日副本通关{0}次","windowId":57002},{"day":3,"param":[50],"point":100,"rwId":51145,"str":"每日副本通关{0}次","windowId":57002},{"day":4,"param":[1],"point":100,"rwId":51158,"str":"通关虚空之境{0}次","subType":18,"windowId":59200},{"day":4,"param":[2],"point":100,"rwId":51159,"str":"通关虚空之境{0}次","subType":18,"windowId":59200},{"day":4,"param":[3],"point":100,"rwId":51160,"str":"通关虚空之境{0}次","subType":18,"windowId":59200},{"day":4,"param":[5],"point":100,"rwId":51161,"str":"通关虚空之境{0}次","subType":18,"windowId":59200},{"day":4,"param":[7],"point":100,"rwId":51162,"str":"通关虚空之境{0}次","subType":18,"windowId":59200},{"day":4,"param":[10],"point":100,"rwId":51163,"str":"通关虚空之境{0}次","subType":18,"windowId":59200},{"day":4,"param":[15],"point":100,"rwId":51164,"str":"通关虚空之境{0}次","subType":18,"windowId":59200},{"day":4,"param":[20],"point":100,"rwId":51165,"str":"通关虚空之境{0}次","subType":18,"windowId":59200},{"day":4,"param":[25],"point":100,"rwId":51166,"str":"通关虚空之境{0}次","subType":18,"windowId":59200},{"day":4,"param":[30],"point":100,"rwId":51167,"str":"通关虚空之境{0}次","subType":18,"windowId":59200}],"18":[{"day":4,"param":[5],"point":100,"rwId":51148,"str":"时装培养{0}次","windowId":10120},{"day":4,"param":[10],"point":100,"rwId":51149,"str":"时装培养{0}次","windowId":10120},{"day":4,"param":[15],"point":100,"rwId":51150,"str":"时装培养{0}次","windowId":10120},{"day":4,"param":[20],"point":100,"rwId":51151,"str":"时装培养{0}次","windowId":10120},{"day":4,"param":[30],"point":100,"rwId":51152,"str":"时装培养{0}次","windowId":10120},{"day":4,"param":[40],"point":100,"rwId":51153,"str":"时装培养{0}次","windowId":10120},{"day":4,"param":[50],"point":100,"rwId":51154,"str":"时装培养{0}次","windowId":10120},{"day":4,"param":[60],"point":100,"rwId":51155,"str":"时装培养{0}次","windowId":10120},{"day":4,"param":[80],"point":100,"rwId":51156,"str":"时装培养{0}次","windowId":10120},{"day":4,"param":[100],"point":100,"rwId":51157,"str":"时装培养{0}次","windowId":10120}],"22":[{"day":5,"param":[1],"point":100,"rwId":51170,"str":"宝石等级达到{0}级","windowId":60130},{"day":5,"param":[2],"point":100,"rwId":51171,"str":"宝石等级达到{0}级","windowId":60130},{"day":5,"param":[3],"point":100,"rwId":51172,"str":"宝石等级达到{0}级","windowId":60130},{"day":5,"param":[4],"point":100,"rwId":51173,"str":"宝石等级达到{0}级","windowId":60130},{"day":5,"param":[5],"point":100,"rwId":51174,"str":"宝石等级达到{0}级","windowId":60130}],"23":[{"day":5,"param":[1],"point":100,"rwId":51175,"str":"藏宝图探索{0}次","windowId":20370},{"day":5,"param":[3],"point":100,"rwId":51176,"str":"藏宝图探索{0}次","windowId":20370},{"day":5,"param":[5],"point":100,"rwId":51177,"str":"藏宝图探索{0}次","windowId":20370},{"day":5,"param":[7],"point":100,"rwId":51178,"str":"藏宝图探索{0}次","windowId":20370},{"day":5,"param":[10],"point":100,"rwId":51179,"str":"藏宝图探索{0}次","windowId":20370}],"26":[{"day":6,"param":[5],"point":100,"rwId":51182,"str":"挑战世界boss{0}次","windowId":30500},{"day":6,"param":[10],"point":100,"rwId":51183,"str":"挑战世界boss{0}次","windowId":30500},{"day":6,"param":[20],"point":100,"rwId":51184,"str":"挑战世界boss{0}次","windowId":30500},{"day":6,"param":[30],"point":100,"rwId":51185,"str":"挑战世界boss{0}次","windowId":30500},{"day":6,"param":[50],"point":100,"rwId":51186,"str":"挑战世界boss{0}次","windowId":30500}],"27":[{"day":6,"param":[11],"point":100,"rwId":51187,"str":"人物等级达到{0}级","windowId":1},{"day":6,"param":[13],"point":100,"rwId":51188,"str":"人物等级达到{0}级","windowId":1},{"day":6,"param":[15],"point":100,"rwId":51189,"str":"人物等级达到{0}级","windowId":1},{"day":6,"param":[20],"point":100,"rwId":51190,"str":"人物等级达到{0}级","windowId":1},{"day":6,"param":[25],"point":100,"rwId":51191,"str":"人物等级达到{0}级","windowId":1}],"30":[{"day":7,"param":[1],"point":100,"rwId":51194,"str":"家园掠夺{0}次","subType":15,"windowId":20650},{"day":7,"param":[3],"point":100,"rwId":51195,"str":"家园掠夺{0}次","subType":15,"windowId":20650},{"day":7,"param":[5],"point":100,"rwId":51196,"str":"家园掠夺{0}次","subType":15,"windowId":20650},{"day":7,"param":[7],"point":100,"rwId":51197,"str":"家园掠夺{0}次","subType":15,"windowId":20650},{"day":7,"param":[9],"point":100,"rwId":51198,"str":"家园掠夺{0}次","subType":15,"windowId":20650},{"day":7,"param":[11],"point":100,"rwId":51199,"str":"家园掠夺{0}次","subType":15,"windowId":20650},{"day":7,"param":[13],"point":100,"rwId":51200,"str":"家园掠夺{0}次","subType":15,"windowId":20650},{"day":7,"param":[15],"point":100,"rwId":51201,"str":"家园掠夺{0}次","subType":15,"windowId":20650},{"day":7,"param":[17],"point":100,"rwId":51202,"str":"家园掠夺{0}次","subType":15,"windowId":20650},{"day":7,"param":[20],"point":100,"rwId":51203,"str":"家园掠夺{0}次","subType":15,"windowId":20650}],"31":[{"day":7,"param":[5],"point":100,"rwId":51204,"str":"精英爬塔挑战{0}次","windowId":30100},{"day":7,"param":[10],"point":100,"rwId":51205,"str":"精英爬塔挑战{0}次","windowId":30100},{"day":7,"param":[15],"point":100,"rwId":51206,"str":"精英爬塔挑战{0}次","windowId":30100},{"day":7,"param":[20],"point":100,"rwId":51207,"str":"精英爬塔挑战{0}次","windowId":30100},{"day":7,"param":[25],"point":100,"rwId":51208,"str":"精英爬塔挑战{0}次","windowId":30100},{"day":7,"param":[30],"point":100,"rwId":51209,"str":"精英爬塔挑战{0}次","windowId":30100}],"33":[{"day":1,"rwId":51211,"str":"超值礼包"},{"day":2,"rwId":51212,"str":"超值礼包"},{"day":3,"rwId":51213,"str":"超值礼包"},{"day":4,"rwId":51214,"str":"超值礼包"},{"day":5,"rwId":51215,"str":"超值礼包"},{"day":6,"rwId":51216,"str":"超值礼包"},{"day":7,"rwId":51217,"str":"超值礼包"},{"day":1,"rwId":51218,"str":"超值礼包"}]},"score":{"1":[{"reward":[{"count":25,"id":2034,"type":0}],"value":1200},{"reward":[{"count":35,"id":20062,"type":0}],"value":4200},{"reward":[{"count":65,"id":20062,"type":0}],"value":7300},{"reward":[{"count":1,"id":10406,"type":0}],"value":10000}]},"task":{"1":[{"reward":1,"task":1,"type":1},{"reward":2,"task":1,"type":2},{"reward":3,"task":1,"type":4},{"reward":6,"task":1,"type":10},{"reward":7,"task":1,"type":5},{"reward":33,"task":1,"type":14},{"reward":1,"task":2,"type":1},{"reward":9,"task":2,"type":6},{"reward":11,"task":2,"type":3},{"reward":7,"task":2,"type":5},{"reward":33,"task":2,"type":14},{"reward":1,"task":3,"type":1},{"reward":14,"task":3,"type":7},{"reward":15,"task":3,"type":8},{"reward":7,"task":3,"type":5},{"reward":33,"task":3,"type":14},{"reward":1,"task":4,"type":1},{"reward":18,"task":4,"type":17},{"reward":15,"task":4,"type":8},{"reward":7,"task":4,"type":5},{"reward":33,"task":4,"type":14},{"reward":1,"task":5,"type":1},{"reward":22,"task":5,"type":16},{"reward":23,"task":5,"type":11},{"reward":7,"task":5,"type":5},{"reward":33,"task":5,"type":14},{"reward":1,"task":6,"type":1},{"reward":26,"task":6,"type":9},{"reward":27,"task":6,"type":15},{"reward":7,"task":6,"type":5},{"reward":33,"task":6,"type":14},{"reward":1,"task":7,"type":1},{"reward":30,"task":7,"type":13},{"reward":31,"task":7,"type":12},{"reward":7,"task":7,"type":5},{"reward":33,"task":7,"type":14}]},"taskName":{"1":{"taskName":"登录游戏"},"2":{"taskName":"主线副本"},"3":{"taskName":"远征"},"4":{"taskName":"卡牌"},"5":{"taskName":"充值金额"},"6":{"taskName":"装备"},"7":{"taskName":"神器"},"8":{"taskName":"每日副本"},"9":{"taskName":"世界boss"},"10":{"taskName":"祭坛"},"11":{"taskName":"藏宝图"},"12":{"taskName":"图腾副本"},"13":{"taskName":"家园"},"14":{"taskName":"特惠礼包"},"15":{"taskName":"人物等级"},"16":{"taskName":"宝石"},"17":{"taskName":"时装"}}}}