[{"__type__":"cc.SpriteFrame","content":{"name":"Ttile","texture":"68u/8v67pNJrhlaYQagsNJ","rect":[519,302,143,64],"offset":[1,-1],"originalSize":[147,70],"capInsets":[0,0,0,0]}},{"__type__":"cc.SpriteFrame","content":{"name":"DiaLogBox","texture":"68u/8v67pNJrhlaYQagsNJ","rect":[433,1,432,299],"offset":[0,0],"originalSize":[432,299],"capInsets":[0,0,0,0]}},{"__type__":"cc.SpriteFrame","content":{"name":"ReadMail","texture":"68u/8v67pNJrhlaYQagsNJ","rect":[664,302,66,58],"offset":[0,0],"originalSize":[66,58],"capInsets":[0,0,0,0]}},{"__type__":"cc.SpriteFrame","content":{"name":"AwardText","texture":"68u/8v67pNJrhlaYQagsNJ","rect":[389,320,128,33],"offset":[0,0],"originalSize":[128,33],"capInsets":[0,0,0,0]}},{"__type__":"cc.SpriteFrame","content":{"name":"AwardMail","texture":"68u/8v67pNJrhlaYQagsNJ","rect":[732,302,66,50],"offset":[0,-4],"originalSize":[66,58],"capInsets":[0,0,0,0]}},{"__type__":"cc.SpriteFrame","content":{"name":"bg_1","texture":"68u/8v67pNJrhlaYQagsNJ","rect":[1,1,430,317],"offset":[0,0],"originalSize":[430,317],"capInsets":[0,0,0,0]}},{"__type__":"cc.SpriteFrame","content":{"name":"label_1","texture":"68u/8v67pNJrhlaYQagsNJ","rect":[1,320,386,34],"offset":[0,0],"originalSize":[386,34],"capInsets":[13,11,13,11]}},{"__type__":"cc.SpriteAtlas","_name":"Mail.plist","_spriteFrames":{"AwardMail":{"__uuid__":"5aNLruLZZK+JuWZsCE+UAR"},"AwardText":{"__uuid__":"4et8rhYSNAwK45dEJuDMLr"},"DiaLogBox":{"__uuid__":"185bVcWO5PyJ7Zbym90ToU"},"ReadMail":{"__uuid__":"43uK58aMREG6TaqXXbtgQh"},"Red":{"__uuid__":"a8mQuquRtNyamPyCHTf1JI"},"Ttile":{"__uuid__":"02WgHA41dG6KZq4zYYWmkH"},"UnReadMial":{"__uuid__":"c7u1oo8kJBn6Y7R1F0v7TU"},"bg_1":{"__uuid__":"64cN6n13tIsKntfdHIBlDB"},"label_1":{"__uuid__":"86ljbqjLtBoKSos57THZjy"}}},{"__type__":"cc.SpriteFrame","content":{"name":"Red","texture":"68u/8v67pNJrhlaYQagsNJ","rect":[867,1,23,25],"offset":[0,0],"originalSize":[23,25],"capInsets":[0,0,0,0]}},{"__type__":"cc.SpriteFrame","content":{"name":"UnReadMial","texture":"68u/8v67pNJrhlaYQagsNJ","rect":[800,302,66,50],"offset":[0,-4],"originalSize":[66,58],"capInsets":[0,0,0,0]}}]