[{"__type__":"cc.SpriteFrame","content":{"name":"bg_kunnan","texture":"3fLCwpOldIPojKOMUfI4Sw","rect":[585,1,290,359],"offset":[0,0],"originalSize":[290,359],"capInsets":[0,0,0,0]}},{"__type__":"cc.SpriteFrame","content":{"name":"bg_jiandan","texture":"3fLCwpOldIPojKOMUfI4Sw","rect":[1,1,290,361],"offset":[0,0],"originalSize":[290,361],"capInsets":[0,0,0,0]}},{"__type__":"cc.SpriteFrame","content":{"name":"bg_putong","texture":"3fLCwpOldIPojKOMUfI4Sw","rect":[293,1,290,361],"offset":[0,0],"originalSize":[290,361],"capInsets":[0,0,0,0]}},{"__type__":"cc.SpriteAtlas","_name":"difficulty.plist","_spriteFrames":{"bg_jiandan":{"__uuid__":"90BvWRC4tOd5Yn/JEyy/z6"},"bg_kunnan":{"__uuid__":"5dosOdoANI9qn2E9mJB1+d"},"bg_putong":{"__uuid__":"90J45oUF1ET6WCcLWXovVU"}}}]