[[{"__type__":"cc.Prefab","_name":"RoleStrengthenStar","data":{"__id__":1}},{"__type__":"cc.Node","_name":"RoleStrengthenStar","_children":[{"__id__":2}],"_prefab":{"__type__":"cc.PrefabInfo","root":{"__id__":1},"asset":{"__uuid__":"46B6xq2/VFypTGLqWJkKnf"},"fileId":"4ddb6GB+FKfYGgnzQgX88V"},"_contentSize":{"__type__":"cc.Size","width":21,"height":21},"_trs":{"__type__":"TypedArray","ctor":"Float64Array","array":[0,0,0,0,0,0,1,1,1,1]}},{"__type__":"cc.Node","_name":"spriteStar","_parent":{"__id__":1},"_components":[{"__type__":"cc.Sprite","node":{"__id__":2},"_spriteFrame":{"__uuid__":"f4EgxMdUhN7KT+C7zpOSoB"}}],"_prefab":{"__type__":"cc.PrefabInfo","root":{"__id__":1},"asset":{"__uuid__":"46B6xq2/VFypTGLqWJkKnf"},"fileId":"80O2zbJXhB2a2tEWsH9+CS"},"_contentSize":{"__type__":"cc.Size","width":21,"height":21},"_trs":{"__type__":"TypedArray","ctor":"Float64Array","array":[0,0,0,0,0,0,1,1,1,1]}}],{"__type__":"cc.SpriteFrame","content":{"name":"icon_wybq5","texture":"db8wAH5W9NoICETm0pzi7O","rect":[135,50,21,21],"offset":[0,0],"originalSize":[21,21],"capInsets":[0,0,0,0]}}]